Workbook

Sheet Harbor Bay assumptions
A1: Harbor Bay assumptions
A2: Atlas Commerce — Harbor Bay · Base
A4: Variable / dimension | B4: Harbor Bay
A5: Monthly visits | B5: =50000 -> 50000
A6: Conversion rate | B6: =0.025 -> 0.025
A7: Average order value | B7: =85 -> 85
A8: Product cost per order (provisional) | B8: ='Harbor Bay assumptions'!B7*'Catalog product-cost estimation'!B7 -> 42.774903
A9: Fulfillment cost per order | B9: =12 -> 12
A10: Campaign spend per month | B10: =15000 -> 15000
A11: Inference cost per month | B11: =3000 -> 3000
A12: Infrastructure cost per month (synthetic demo) | B12: =500 -> 500
A13: Opening cash (synthetic demo) | B13: =30000 -> 30000

Sheet Harbor Bay monthly P&L and cash
A1: Harbor Bay monthly P&L and cash
A2: Atlas Commerce — Harbor Bay · Base
A4: Variable / dimension | B4: 2026-10 | C4: 2026-11 | D4: 2026-12 | E4: 2027-01 | F4: 2027-02 | G4: 2027-03 | H4: 2027-04 | I4: 2027-05 | J4: 2027-06 | K4: 2027-07 | L4: 2027-08 | M4: 2027-09 | N4: 2027-10 | O4: 2027-11 | P4: 2027-12
A5: Visits | B5: =SUM('Harbor Bay monthly P&L and cash'!B6) -> 50000 | C5: =SUM('Harbor Bay monthly P&L and cash'!C6) -> 50000 | D5: =SUM('Harbor Bay monthly P&L and cash'!D6) -> 50000 | E5: =SUM('Harbor Bay monthly P&L and cash'!E6) -> 50000 | F5: =SUM('Harbor Bay monthly P&L and cash'!F6) -> 50000 | G5: =SUM('Harbor Bay monthly P&L and cash'!G6) -> 50000 | H5: =SUM('Harbor Bay monthly P&L and cash'!H6) -> 50000 | I5: =SUM('Harbor Bay monthly P&L and cash'!I6) -> 50000 | ... P5: =SUM('Harbor Bay monthly P&L and cash'!P6) -> 50000
A6: Harbor Bay | B6: =IF('Harbor Bay assumptions'!B5="","",'Harbor Bay assumptions'!B5) -> 50000 | C6: =IF('Harbor Bay assumptions'!B5="","",'Harbor Bay assumptions'!B5) -> 50000 | D6: =IF('Harbor Bay assumptions'!B5="","",'Harbor Bay assumptions'!B5) -> 50000 | E6: =IF('Harbor Bay assumptions'!B5="","",'Harbor Bay assumptions'!B5) -> 50000 | F6: =IF('Harbor Bay assumptions'!B5="","",'Harbor Bay assumptions'!B5) -> 50000 | G6: =IF('Harbor Bay assumptions'!B5="","",'Harbor Bay assumptions'!B5) -> 50000 | H6: =IF('Harbor Bay assumptions'!B5="","",'Harbor Bay assumptions'!B5) -> 50000 | I6: =IF('Harbor Bay assumptions'!B5="","",'Harbor Bay assumptions'!B5) -> 50000 | J6: =IF('Harbor Bay assumptions'!B5="","",'Harbor Bay assumptions'!B5) -> 50000 | K6: =IF('Harbor Bay assumptions'!B5="","",'Harbor Bay assumptions'!B5) -> 50000 | L6: =IF('Harbor Bay assumptions'!B5="","",'Harbor Bay assumptions'!B5) -> 50000 | M6: =IF('Harbor Bay assumptions'!B5="","",'Harbor Bay assumptions'!B5) -> 50000 | N6: =IF('Harbor Bay assumptions'!B5="","",'Harbor Bay assumptions'!B5) -> 50000 | O6: =IF('Harbor Bay assumptions'!B5="","",'Harbor Bay assumptions'!B5) -> 50000 | P6: =IF('Harbor Bay assumptions'!B5="","",'Harbor Bay assumptions'!B5) -> 50000
A7: Orders | B7: =SUM('Harbor Bay monthly P&L and cash'!B8) -> 1250 | C7: =SUM('Harbor Bay monthly P&L and cash'!C8) -> 1250 | D7: =SUM('Harbor Bay monthly P&L and cash'!D8) -> 1250 | E7: =SUM('Harbor Bay monthly P&L and cash'!E8) -> 1250 | F7: =SUM('Harbor Bay monthly P&L and cash'!F8) -> 1250 | G7: =SUM('Harbor Bay monthly P&L and cash'!G8) -> 1250 | H7: =SUM('Harbor Bay monthly P&L and cash'!H8) -> 1250 | I7: =SUM('Harbor Bay monthly P&L and cash'!I8) -> 1250 | ... P7: =SUM('Harbor Bay monthly P&L and cash'!P8) -> 1250
A8: Harbor Bay | B8: ='Harbor Bay monthly P&L and cash'!B6*'Harbor Bay assumptions'!B6 -> 1250 | C8: ='Harbor Bay monthly P&L and cash'!C6*'Harbor Bay assumptions'!B6 -> 1250 | D8: ='Harbor Bay monthly P&L and cash'!D6*'Harbor Bay assumptions'!B6 -> 1250 | E8: ='Harbor Bay monthly P&L and cash'!E6*'Harbor Bay assumptions'!B6 -> 1250 | F8: ='Harbor Bay monthly P&L and cash'!F6*'Harbor Bay assumptions'!B6 -> 1250 | G8: ='Harbor Bay monthly P&L and cash'!G6*'Harbor Bay assumptions'!B6 -> 1250 | H8: ='Harbor Bay monthly P&L and cash'!H6*'Harbor Bay assumptions'!B6 -> 1250 | I8: ='Harbor Bay monthly P&L and cash'!I6*'Harbor Bay assumptions'!B6 -> 1250 | J8: ='Harbor Bay monthly P&L and cash'!J6*'Harbor Bay assumptions'!B6 -> 1250 | K8: ='Harbor Bay monthly P&L and cash'!K6*'Harbor Bay assumptions'!B6 -> 1250 | L8: ='Harbor Bay monthly P&L and cash'!L6*'Harbor Bay assumptions'!B6 -> 1250 | M8: ='Harbor Bay monthly P&L and cash'!M6*'Harbor Bay assumptions'!B6 -> 1250 | N8: ='Harbor Bay monthly P&L and cash'!N6*'Harbor Bay assumptions'!B6 -> 1250 | O8: ='Harbor Bay monthly P&L and cash'!O6*'Harbor Bay assumptions'!B6 -> 1250 | P8: ='Harbor Bay monthly P&L and cash'!P6*'Harbor Bay assumptions'!B6 -> 1250
A9: Revenue | B9: =SUM('Harbor Bay monthly P&L and cash'!B10) -> 106250 | C9: =SUM('Harbor Bay monthly P&L and cash'!C10) -> 106250 | D9: =SUM('Harbor Bay monthly P&L and cash'!D10) -> 106250 | E9: =SUM('Harbor Bay monthly P&L and cash'!E10) -> 106250 | F9: =SUM('Harbor Bay monthly P&L and cash'!F10) -> 106250 | G9: =SUM('Harbor Bay monthly P&L and cash'!G10) -> 106250 | H9: =SUM('Harbor Bay monthly P&L and cash'!H10) -> 106250 | I9: =SUM('Harbor Bay monthly P&L and cash'!I10) -> 106250 | ... P9: =SUM('Harbor Bay monthly P&L and cash'!P10) -> 106250
A10: Harbor Bay | B10: ='Harbor Bay monthly P&L and cash'!B8*'Harbor Bay assumptions'!B7 -> 106250 | C10: ='Harbor Bay monthly P&L and cash'!C8*'Harbor Bay assumptions'!B7 -> 106250 | D10: ='Harbor Bay monthly P&L and cash'!D8*'Harbor Bay assumptions'!B7 -> 106250 | E10: ='Harbor Bay monthly P&L and cash'!E8*'Harbor Bay assumptions'!B7 -> 106250 | F10: ='Harbor Bay monthly P&L and cash'!F8*'Harbor Bay assumptions'!B7 -> 106250 | G10: ='Harbor Bay monthly P&L and cash'!G8*'Harbor Bay assumptions'!B7 -> 106250 | H10: ='Harbor Bay monthly P&L and cash'!H8*'Harbor Bay assumptions'!B7 -> 106250 | I10: ='Harbor Bay monthly P&L and cash'!I8*'Harbor Bay assumptions'!B7 -> 106250 | J10: ='Harbor Bay monthly P&L and cash'!J8*'Harbor Bay assumptions'!B7 -> 106250 | K10: ='Harbor Bay monthly P&L and cash'!K8*'Harbor Bay assumptions'!B7 -> 106250 | L10: ='Harbor Bay monthly P&L and cash'!L8*'Harbor Bay assumptions'!B7 -> 106250 | M10: ='Harbor Bay monthly P&L and cash'!M8*'Harbor Bay assumptions'!B7 -> 106250 | N10: ='Harbor Bay monthly P&L and cash'!N8*'Harbor Bay assumptions'!B7 -> 106250 | O10: ='Harbor Bay monthly P&L and cash'!O8*'Harbor Bay assumptions'!B7 -> 106250 | P10: ='Harbor Bay monthly P&L and cash'!P8*'Harbor Bay assumptions'!B7 -> 106250
A11: Product cost | B11: =SUM('Harbor Bay monthly P&L and cash'!B12) -> 53468.629 | C11: =SUM('Harbor Bay monthly P&L and cash'!C12) -> 53468.629 | D11: =SUM('Harbor Bay monthly P&L and cash'!D12) -> 53468.629 | E11: =SUM('Harbor Bay monthly P&L and cash'!E12) -> 53468.629 | F11: =SUM('Harbor Bay monthly P&L and cash'!F12) -> 53468.629 | G11: =SUM('Harbor Bay monthly P&L and cash'!G12) -> 53468.629 | H11: =SUM('Harbor Bay monthly P&L and cash'!H12) -> 53468.629 | I11: =SUM('Harbor Bay monthly P&L and cash'!I12) -> 53468.629 | ... P11: =SUM('Harbor Bay monthly P&L and cash'!P12) -> 53468.629
A12: Harbor Bay | B12: ='Harbor Bay monthly P&L and cash'!B8*'Harbor Bay assumptions'!B8 -> 53468.629 | C12: ='Harbor Bay monthly P&L and cash'!C8*'Harbor Bay assumptions'!B8 -> 53468.629 | D12: ='Harbor Bay monthly P&L and cash'!D8*'Harbor Bay assumptions'!B8 -> 53468.629 | E12: ='Harbor Bay monthly P&L and cash'!E8*'Harbor Bay assumptions'!B8 -> 53468.629 | F12: ='Harbor Bay monthly P&L and cash'!F8*'Harbor Bay assumptions'!B8 -> 53468.629 | G12: ='Harbor Bay monthly P&L and cash'!G8*'Harbor Bay assumptions'!B8 -> 53468.629 | H12: ='Harbor Bay monthly P&L and cash'!H8*'Harbor Bay assumptions'!B8 -> 53468.629 | I12: ='Harbor Bay monthly P&L and cash'!I8*'Harbor Bay assumptions'!B8 -> 53468.629 | J12: ='Harbor Bay monthly P&L and cash'!J8*'Harbor Bay assumptions'!B8 -> 53468.629 | K12: ='Harbor Bay monthly P&L and cash'!K8*'Harbor Bay assumptions'!B8 -> 53468.629 | L12: ='Harbor Bay monthly P&L and cash'!L8*'Harbor Bay assumptions'!B8 -> 53468.629 | M12: ='Harbor Bay monthly P&L and cash'!M8*'Harbor Bay assumptions'!B8 -> 53468.629 | N12: ='Harbor Bay monthly P&L and cash'!N8*'Harbor Bay assumptions'!B8 -> 53468.629 | O12: ='Harbor Bay monthly P&L and cash'!O8*'Harbor Bay assumptions'!B8 -> 53468.629 | P12: ='Harbor Bay monthly P&L and cash'!P8*'Harbor Bay assumptions'!B8 -> 53468.629
A13: Fulfillment cost | B13: =SUM('Harbor Bay monthly P&L and cash'!B14) -> 15000 | C13: =SUM('Harbor Bay monthly P&L and cash'!C14) -> 15000 | D13: =SUM('Harbor Bay monthly P&L and cash'!D14) -> 15000 | E13: =SUM('Harbor Bay monthly P&L and cash'!E14) -> 15000 | F13: =SUM('Harbor Bay monthly P&L and cash'!F14) -> 15000 | G13: =SUM('Harbor Bay monthly P&L and cash'!G14) -> 15000 | H13: =SUM('Harbor Bay monthly P&L and cash'!H14) -> 15000 | I13: =SUM('Harbor Bay monthly P&L and cash'!I14) -> 15000 | ... P13: =SUM('Harbor Bay monthly P&L and cash'!P14) -> 15000
A14: Harbor Bay | B14: ='Harbor Bay monthly P&L and cash'!B8*'Harbor Bay assumptions'!B9 -> 15000 | C14: ='Harbor Bay monthly P&L and cash'!C8*'Harbor Bay assumptions'!B9 -> 15000 | D14: ='Harbor Bay monthly P&L and cash'!D8*'Harbor Bay assumptions'!B9 -> 15000 | E14: ='Harbor Bay monthly P&L and cash'!E8*'Harbor Bay assumptions'!B9 -> 15000 | F14: ='Harbor Bay monthly P&L and cash'!F8*'Harbor Bay assumptions'!B9 -> 15000 | G14: ='Harbor Bay monthly P&L and cash'!G8*'Harbor Bay assumptions'!B9 -> 15000 | H14: ='Harbor Bay monthly P&L and cash'!H8*'Harbor Bay assumptions'!B9 -> 15000 | I14: ='Harbor Bay monthly P&L and cash'!I8*'Harbor Bay assumptions'!B9 -> 15000 | J14: ='Harbor Bay monthly P&L and cash'!J8*'Harbor Bay assumptions'!B9 -> 15000 | K14: ='Harbor Bay monthly P&L and cash'!K8*'Harbor Bay assumptions'!B9 -> 15000 | L14: ='Harbor Bay monthly P&L and cash'!L8*'Harbor Bay assumptions'!B9 -> 15000 | M14: ='Harbor Bay monthly P&L and cash'!M8*'Harbor Bay assumptions'!B9 -> 15000 | N14: ='Harbor Bay monthly P&L and cash'!N8*'Harbor Bay assumptions'!B9 -> 15000 | O14: ='Harbor Bay monthly P&L and cash'!O8*'Harbor Bay assumptions'!B9 -> 15000 | P14: ='Harbor Bay monthly P&L and cash'!P8*'Harbor Bay assumptions'!B9 -> 15000
A15: Gross profit | B15: =SUM('Harbor Bay monthly P&L and cash'!B16) -> 37781.371 | C15: =SUM('Harbor Bay monthly P&L and cash'!C16) -> 37781.371 | D15: =SUM('Harbor Bay monthly P&L and cash'!D16) -> 37781.371 | E15: =SUM('Harbor Bay monthly P&L and cash'!E16) -> 37781.371 | F15: =SUM('Harbor Bay monthly P&L and cash'!F16) -> 37781.371 | G15: =SUM('Harbor Bay monthly P&L and cash'!G16) -> 37781.371 | H15: =SUM('Harbor Bay monthly P&L and cash'!H16) -> 37781.371 | I15: =SUM('Harbor Bay monthly P&L and cash'!I16) -> 37781.371 | ... P15: =SUM('Harbor Bay monthly P&L and cash'!P16) -> 37781.371
A16: Harbor Bay | B16: ='Harbor Bay monthly P&L and cash'!B10-'Harbor Bay monthly P&L and cash'!B12-'Harbor Bay monthly P&L and cash'!B14 -> 37781.371 | C16: ='Harbor Bay monthly P&L and cash'!C10-'Harbor Bay monthly P&L and cash'!C12-'Harbor Bay monthly P&L and cash'!C14 -> 37781.371 | D16: ='Harbor Bay monthly P&L and cash'!D10-'Harbor Bay monthly P&L and cash'!D12-'Harbor Bay monthly P&L and cash'!D14 -> 37781.371 | E16: ='Harbor Bay monthly P&L and cash'!E10-'Harbor Bay monthly P&L and cash'!E12-'Harbor Bay monthly P&L and cash'!E14 -> 37781.371 | F16: ='Harbor Bay monthly P&L and cash'!F10-'Harbor Bay monthly P&L and cash'!F12-'Harbor Bay monthly P&L and cash'!F14 -> 37781.371 | G16: ='Harbor Bay monthly P&L and cash'!G10-'Harbor Bay monthly P&L and cash'!G12-'Harbor Bay monthly P&L and cash'!G14 -> 37781.371 | H16: ='Harbor Bay monthly P&L and cash'!H10-'Harbor Bay monthly P&L and cash'!H12-'Harbor Bay monthly P&L and cash'!H14 -> 37781.371 | I16: ='Harbor Bay monthly P&L and cash'!I10-'Harbor Bay monthly P&L and cash'!I12-'Harbor Bay monthly P&L and cash'!I14 -> 37781.371 | ... P16: ='Harbor Bay monthly P&L and cash'!P10-'Harbor Bay monthly P&L and cash'!P12-'Harbor Bay monthly P&L and cash'!P14 -> 37781.371
A17: Gross margin | B17: =IFERROR('Harbor Bay monthly P&L and cash'!B15/'Harbor Bay monthly P&L and cash'!B9,"") -> 0.35558938 | C17: =IFERROR('Harbor Bay monthly P&L and cash'!C15/'Harbor Bay monthly P&L and cash'!C9,"") -> 0.35558938 | D17: =IFERROR('Harbor Bay monthly P&L and cash'!D15/'Harbor Bay monthly P&L and cash'!D9,"") -> 0.35558938 | E17: =IFERROR('Harbor Bay monthly P&L and cash'!E15/'Harbor Bay monthly P&L and cash'!E9,"") -> 0.35558938 | F17: =IFERROR('Harbor Bay monthly P&L and cash'!F15/'Harbor Bay monthly P&L and cash'!F9,"") -> 0.35558938 | G17: =IFERROR('Harbor Bay monthly P&L and cash'!G15/'Harbor Bay monthly P&L and cash'!G9,"") -> 0.35558938 | H17: =IFERROR('Harbor Bay monthly P&L and cash'!H15/'Harbor Bay monthly P&L and cash'!H9,"") -> 0.35558938 | I17: =IFERROR('Harbor Bay monthly P&L and cash'!I15/'Harbor Bay monthly P&L and cash'!I9,"") -> 0.35558938 | ... P17: =IFERROR('Harbor Bay monthly P&L and cash'!P15/'Harbor Bay monthly P&L and cash'!P9,"") -> 0.35558938
A18: Harbor Bay | B18: =IFERROR('Harbor Bay monthly P&L and cash'!B16/'Harbor Bay monthly P&L and cash'!B10,"") -> 0.35558938 | C18: =IFERROR('Harbor Bay monthly P&L and cash'!C16/'Harbor Bay monthly P&L and cash'!C10,"") -> 0.35558938 | D18: =IFERROR('Harbor Bay monthly P&L and cash'!D16/'Harbor Bay monthly P&L and cash'!D10,"") -> 0.35558938 | E18: =IFERROR('Harbor Bay monthly P&L and cash'!E16/'Harbor Bay monthly P&L and cash'!E10,"") -> 0.35558938 | F18: =IFERROR('Harbor Bay monthly P&L and cash'!F16/'Harbor Bay monthly P&L and cash'!F10,"") -> 0.35558938 | G18: =IFERROR('Harbor Bay monthly P&L and cash'!G16/'Harbor Bay monthly P&L and cash'!G10,"") -> 0.35558938 | H18: =IFERROR('Harbor Bay monthly P&L and cash'!H16/'Harbor Bay monthly P&L and cash'!H10,"") -> 0.35558938 | I18: =IFERROR('Harbor Bay monthly P&L and cash'!I16/'Harbor Bay monthly P&L and cash'!I10,"") -> 0.35558938 | ... P18: =IFERROR('Harbor Bay monthly P&L and cash'!P16/'Harbor Bay monthly P&L and cash'!P10,"") -> 0.35558938
A19: Campaign expense | B19: =SUM('Harbor Bay monthly P&L and cash'!B20) -> 15000 | C19: =SUM('Harbor Bay monthly P&L and cash'!C20) -> 15000 | D19: =SUM('Harbor Bay monthly P&L and cash'!D20) -> 15000 | E19: =SUM('Harbor Bay monthly P&L and cash'!E20) -> 15000 | F19: =SUM('Harbor Bay monthly P&L and cash'!F20) -> 15000 | G19: =SUM('Harbor Bay monthly P&L and cash'!G20) -> 15000 | H19: =SUM('Harbor Bay monthly P&L and cash'!H20) -> 15000 | I19: =SUM('Harbor Bay monthly P&L and cash'!I20) -> 15000 | ... P19: =SUM('Harbor Bay monthly P&L and cash'!P20) -> 15000
A20: Harbor Bay | B20: =IF('Harbor Bay assumptions'!B10="","",'Harbor Bay assumptions'!B10) -> 15000 | C20: =IF('Harbor Bay assumptions'!B10="","",'Harbor Bay assumptions'!B10) -> 15000 | D20: =IF('Harbor Bay assumptions'!B10="","",'Harbor Bay assumptions'!B10) -> 15000 | E20: =IF('Harbor Bay assumptions'!B10="","",'Harbor Bay assumptions'!B10) -> 15000 | F20: =IF('Harbor Bay assumptions'!B10="","",'Harbor Bay assumptions'!B10) -> 15000 | G20: =IF('Harbor Bay assumptions'!B10="","",'Harbor Bay assumptions'!B10) -> 15000 | H20: =IF('Harbor Bay assumptions'!B10="","",'Harbor Bay assumptions'!B10) -> 15000 | I20: =IF('Harbor Bay assumptions'!B10="","",'Harbor Bay assumptions'!B10) -> 15000 | J20: =IF('Harbor Bay assumptions'!B10="","",'Harbor Bay assumptions'!B10) -> 15000 | K20: =IF('Harbor Bay assumptions'!B10="","",'Harbor Bay assumptions'!B10) -> 15000 | L20: =IF('Harbor Bay assumptions'!B10="","",'Harbor Bay assumptions'!B10) -> 15000 | M20: =IF('Harbor Bay assumptions'!B10="","",'Harbor Bay assumptions'!B10) -> 15000 | N20: =IF('Harbor Bay assumptions'!B10="","",'Harbor Bay assumptions'!B10) -> 15000 | O20: =IF('Harbor Bay assumptions'!B10="","",'Harbor Bay assumptions'!B10) -> 15000 | P20: =IF('Harbor Bay assumptions'!B10="","",'Harbor Bay assumptions'!B10) -> 15000
A21: Inference expense | B21: =SUM('Harbor Bay monthly P&L and cash'!B22) -> 3000 | C21: =SUM('Harbor Bay monthly P&L and cash'!C22) -> 3000 | D21: =SUM('Harbor Bay monthly P&L and cash'!D22) -> 3000 | E21: =SUM('Harbor Bay monthly P&L and cash'!E22) -> 3000 | F21: =SUM('Harbor Bay monthly P&L and cash'!F22) -> 3000 | G21: =SUM('Harbor Bay monthly P&L and cash'!G22) -> 3000 | H21: =SUM('Harbor Bay monthly P&L and cash'!H22) -> 3000 | I21: =SUM('Harbor Bay monthly P&L and cash'!I22) -> 3000 | ... P21: =SUM('Harbor Bay monthly P&L and cash'!P22) -> 3000
A22: Harbor Bay | B22: =IF('Harbor Bay assumptions'!B11="","",'Harbor Bay assumptions'!B11) -> 3000 | C22: =IF('Harbor Bay assumptions'!B11="","",'Harbor Bay assumptions'!B11) -> 3000 | D22: =IF('Harbor Bay assumptions'!B11="","",'Harbor Bay assumptions'!B11) -> 3000 | E22: =IF('Harbor Bay assumptions'!B11="","",'Harbor Bay assumptions'!B11) -> 3000 | F22: =IF('Harbor Bay assumptions'!B11="","",'Harbor Bay assumptions'!B11) -> 3000 | G22: =IF('Harbor Bay assumptions'!B11="","",'Harbor Bay assumptions'!B11) -> 3000 | H22: =IF('Harbor Bay assumptions'!B11="","",'Harbor Bay assumptions'!B11) -> 3000 | I22: =IF('Harbor Bay assumptions'!B11="","",'Harbor Bay assumptions'!B11) -> 3000 | J22: =IF('Harbor Bay assumptions'!B11="","",'Harbor Bay assumptions'!B11) -> 3000 | K22: =IF('Harbor Bay assumptions'!B11="","",'Harbor Bay assumptions'!B11) -> 3000 | L22: =IF('Harbor Bay assumptions'!B11="","",'Harbor Bay assumptions'!B11) -> 3000 | M22: =IF('Harbor Bay assumptions'!B11="","",'Harbor Bay assumptions'!B11) -> 3000 | N22: =IF('Harbor Bay assumptions'!B11="","",'Harbor Bay assumptions'!B11) -> 3000 | O22: =IF('Harbor Bay assumptions'!B11="","",'Harbor Bay assumptions'!B11) -> 3000 | P22: =IF('Harbor Bay assumptions'!B11="","",'Harbor Bay assumptions'!B11) -> 3000
A23: Infrastructure expense | B23: =IF('Harbor Bay assumptions'!B12="","",'Harbor Bay assumptions'!B12) -> 500 | C23: =IF('Harbor Bay assumptions'!B12="","",'Harbor Bay assumptions'!B12) -> 500 | D23: =IF('Harbor Bay assumptions'!B12="","",'Harbor Bay assumptions'!B12) -> 500 | E23: =IF('Harbor Bay assumptions'!B12="","",'Harbor Bay assumptions'!B12) -> 500 | F23: =IF('Harbor Bay assumptions'!B12="","",'Harbor Bay assumptions'!B12) -> 500 | G23: =IF('Harbor Bay assumptions'!B12="","",'Harbor Bay assumptions'!B12) -> 500 | H23: =IF('Harbor Bay assumptions'!B12="","",'Harbor Bay assumptions'!B12) -> 500 | I23: =IF('Harbor Bay assumptions'!B12="","",'Harbor Bay assumptions'!B12) -> 500 | J23: =IF('Harbor Bay assumptions'!B12="","",'Harbor Bay assumptions'!B12) -> 500 | K23: =IF('Harbor Bay assumptions'!B12="","",'Harbor Bay assumptions'!B12) -> 500 | L23: =IF('Harbor Bay assumptions'!B12="","",'Harbor Bay assumptions'!B12) -> 500 | M23: =IF('Harbor Bay assumptions'!B12="","",'Harbor Bay assumptions'!B12) -> 500 | N23: =IF('Harbor Bay assumptions'!B12="","",'Harbor Bay assumptions'!B12) -> 500 | O23: =IF('Harbor Bay assumptions'!B12="","",'Harbor Bay assumptions'!B12) -> 500 | P23: =IF('Harbor Bay assumptions'!B12="","",'Harbor Bay assumptions'!B12) -> 500
A24: Harbor Bay | B24: =IF('Harbor Bay assumptions'!B12="","",'Harbor Bay assumptions'!B12) -> 500 | C24: =IF('Harbor Bay assumptions'!B12="","",'Harbor Bay assumptions'!B12) -> 500 | D24: =IF('Harbor Bay assumptions'!B12="","",'Harbor Bay assumptions'!B12) -> 500 | E24: =IF('Harbor Bay assumptions'!B12="","",'Harbor Bay assumptions'!B12) -> 500 | F24: =IF('Harbor Bay assumptions'!B12="","",'Harbor Bay assumptions'!B12) -> 500 | G24: =IF('Harbor Bay assumptions'!B12="","",'Harbor Bay assumptions'!B12) -> 500 | H24: =IF('Harbor Bay assumptions'!B12="","",'Harbor Bay assumptions'!B12) -> 500 | I24: =IF('Harbor Bay assumptions'!B12="","",'Harbor Bay assumptions'!B12) -> 500 | J24: =IF('Harbor Bay assumptions'!B12="","",'Harbor Bay assumptions'!B12) -> 500 | K24: =IF('Harbor Bay assumptions'!B12="","",'Harbor Bay assumptions'!B12) -> 500 | L24: =IF('Harbor Bay assumptions'!B12="","",'Harbor Bay assumptions'!B12) -> 500 | M24: =IF('Harbor Bay assumptions'!B12="","",'Harbor Bay assumptions'!B12) -> 500 | N24: =IF('Harbor Bay assumptions'!B12="","",'Harbor Bay assumptions'!B12) -> 500 | O24: =IF('Harbor Bay assumptions'!B12="","",'Harbor Bay assumptions'!B12) -> 500 | P24: =IF('Harbor Bay assumptions'!B12="","",'Harbor Bay assumptions'!B12) -> 500
A25: Contribution | B25: =IF('Harbor Bay monthly P&L and cash'!B23="","",'Harbor Bay monthly P&L and cash'!B15-'Harbor Bay monthly P&L and cash'!B19-'Harbor Bay monthly P&L and cash'!B21-'Harbor Bay monthly P&L and cash'!B23) -> 19281.371 | C25: =IF('Harbor Bay monthly P&L and cash'!C23="","",'Harbor Bay monthly P&L and cash'!C15-'Harbor Bay monthly P&L and cash'!C19-'Harbor Bay monthly P&L and cash'!C21-'Harbor Bay monthly P&L and cash'!C23) -> 19281.371 | D25: =IF('Harbor Bay monthly P&L and cash'!D23="","",'Harbor Bay monthly P&L and cash'!D15-'Harbor Bay monthly P&L and cash'!D19-'Harbor Bay monthly P&L and cash'!D21-'Harbor Bay monthly P&L and cash'!D23) -> 19281.371 | E25: =IF('Harbor Bay monthly P&L and cash'!E23="","",'Harbor Bay monthly P&L and cash'!E15-'Harbor Bay monthly P&L and cash'!E19-'Harbor Bay monthly P&L and cash'!E21-'Harbor Bay monthly P&L and cash'!E23) -> 19281.371 | F25: =IF('Harbor Bay monthly P&L and cash'!F23="","",'Harbor Bay monthly P&L and cash'!F15-'Harbor Bay monthly P&L and cash'!F19-'Harbor Bay monthly P&L and cash'!F21-'Harbor Bay monthly P&L and cash'!F23) -> 19281.371 | G25: =IF('Harbor Bay monthly P&L and cash'!G23="","",'Harbor Bay monthly P&L and cash'!G15-'Harbor Bay monthly P&L and cash'!G19-'Harbor Bay monthly P&L and cash'!G21-'Harbor Bay monthly P&L and cash'!G23) -> 19281.371 | H25: =IF('Harbor Bay monthly P&L and cash'!H23="","",'Harbor Bay monthly P&L and cash'!H15-'Harbor Bay monthly P&L and cash'!H19-'Harbor Bay monthly P&L and cash'!H21-'Harbor Bay monthly P&L and cash'!H23) -> 19281.371 | I25: =IF('Harbor Bay monthly P&L and cash'!I23="","",'Harbor Bay monthly P&L and cash'!I15-'Harbor Bay monthly P&L and cash'!I19-'Harbor Bay monthly P&L and cash'!I21-'Harbor Bay monthly P&L and cash'!I23) -> 19281.371 | ... P25: =IF('Harbor Bay monthly P&L and cash'!P23="","",'Harbor Bay monthly P&L and cash'!P15-'Harbor Bay monthly P&L and cash'!P19-'Harbor Bay monthly P&L and cash'!P21-'Harbor Bay monthly P&L and cash'!P23) -> 19281.371
A26: Harbor Bay | B26: =IF('Harbor Bay monthly P&L and cash'!B24="","",'Harbor Bay monthly P&L and cash'!B16-'Harbor Bay monthly P&L and cash'!B20-'Harbor Bay monthly P&L and cash'!B22-'Harbor Bay monthly P&L and cash'!B24) -> 19281.371 | C26: =IF('Harbor Bay monthly P&L and cash'!C24="","",'Harbor Bay monthly P&L and cash'!C16-'Harbor Bay monthly P&L and cash'!C20-'Harbor Bay monthly P&L and cash'!C22-'Harbor Bay monthly P&L and cash'!C24) -> 19281.371 | D26: =IF('Harbor Bay monthly P&L and cash'!D24="","",'Harbor Bay monthly P&L and cash'!D16-'Harbor Bay monthly P&L and cash'!D20-'Harbor Bay monthly P&L and cash'!D22-'Harbor Bay monthly P&L and cash'!D24) -> 19281.371 | E26: =IF('Harbor Bay monthly P&L and cash'!E24="","",'Harbor Bay monthly P&L and cash'!E16-'Harbor Bay monthly P&L and cash'!E20-'Harbor Bay monthly P&L and cash'!E22-'Harbor Bay monthly P&L and cash'!E24) -> 19281.371 | F26: =IF('Harbor Bay monthly P&L and cash'!F24="","",'Harbor Bay monthly P&L and cash'!F16-'Harbor Bay monthly P&L and cash'!F20-'Harbor Bay monthly P&L and cash'!F22-'Harbor Bay monthly P&L and cash'!F24) -> 19281.371 | G26: =IF('Harbor Bay monthly P&L and cash'!G24="","",'Harbor Bay monthly P&L and cash'!G16-'Harbor Bay monthly P&L and cash'!G20-'Harbor Bay monthly P&L and cash'!G22-'Harbor Bay monthly P&L and cash'!G24) -> 19281.371 | H26: =IF('Harbor Bay monthly P&L and cash'!H24="","",'Harbor Bay monthly P&L and cash'!H16-'Harbor Bay monthly P&L and cash'!H20-'Harbor Bay monthly P&L and cash'!H22-'Harbor Bay monthly P&L and cash'!H24) -> 19281.371 | I26: =IF('Harbor Bay monthly P&L and cash'!I24="","",'Harbor Bay monthly P&L and cash'!I16-'Harbor Bay monthly P&L and cash'!I20-'Harbor Bay monthly P&L and cash'!I22-'Harbor Bay monthly P&L and cash'!I24) -> 19281.371 | ... P26: =IF('Harbor Bay monthly P&L and cash'!P24="","",'Harbor Bay monthly P&L and cash'!P16-'Harbor Bay monthly P&L and cash'!P20-'Harbor Bay monthly P&L and cash'!P22-'Harbor Bay monthly P&L and cash'!P24) -> 19281.371
A27: Contribution margin | B27: =IF('Harbor Bay monthly P&L and cash'!B25="","",IFERROR('Harbor Bay monthly P&L and cash'!B25/'Harbor Bay monthly P&L and cash'!B9,"")) -> 0.18147173 | C27: =IF('Harbor Bay monthly P&L and cash'!C25="","",IFERROR('Harbor Bay monthly P&L and cash'!C25/'Harbor Bay monthly P&L and cash'!C9,"")) -> 0.18147173 | D27: =IF('Harbor Bay monthly P&L and cash'!D25="","",IFERROR('Harbor Bay monthly P&L and cash'!D25/'Harbor Bay monthly P&L and cash'!D9,"")) -> 0.18147173 | E27: =IF('Harbor Bay monthly P&L and cash'!E25="","",IFERROR('Harbor Bay monthly P&L and cash'!E25/'Harbor Bay monthly P&L and cash'!E9,"")) -> 0.18147173 | F27: =IF('Harbor Bay monthly P&L and cash'!F25="","",IFERROR('Harbor Bay monthly P&L and cash'!F25/'Harbor Bay monthly P&L and cash'!F9,"")) -> 0.18147173 | G27: =IF('Harbor Bay monthly P&L and cash'!G25="","",IFERROR('Harbor Bay monthly P&L and cash'!G25/'Harbor Bay monthly P&L and cash'!G9,"")) -> 0.18147173 | H27: =IF('Harbor Bay monthly P&L and cash'!H25="","",IFERROR('Harbor Bay monthly P&L and cash'!H25/'Harbor Bay monthly P&L and cash'!H9,"")) -> 0.18147173 | I27: =IF('Harbor Bay monthly P&L and cash'!I25="","",IFERROR('Harbor Bay monthly P&L and cash'!I25/'Harbor Bay monthly P&L and cash'!I9,"")) -> 0.18147173 | ... P27: =IF('Harbor Bay monthly P&L and cash'!P25="","",IFERROR('Harbor Bay monthly P&L and cash'!P25/'Harbor Bay monthly P&L and cash'!P9,"")) -> 0.18147173
A28: Harbor Bay | B28: =IF('Harbor Bay monthly P&L and cash'!B26="","",IFERROR('Harbor Bay monthly P&L and cash'!B26/'Harbor Bay monthly P&L and cash'!B10,"")) -> 0.18147173 | C28: =IF('Harbor Bay monthly P&L and cash'!C26="","",IFERROR('Harbor Bay monthly P&L and cash'!C26/'Harbor Bay monthly P&L and cash'!C10,"")) -> 0.18147173 | D28: =IF('Harbor Bay monthly P&L and cash'!D26="","",IFERROR('Harbor Bay monthly P&L and cash'!D26/'Harbor Bay monthly P&L and cash'!D10,"")) -> 0.18147173 | E28: =IF('Harbor Bay monthly P&L and cash'!E26="","",IFERROR('Harbor Bay monthly P&L and cash'!E26/'Harbor Bay monthly P&L and cash'!E10,"")) -> 0.18147173 | F28: =IF('Harbor Bay monthly P&L and cash'!F26="","",IFERROR('Harbor Bay monthly P&L and cash'!F26/'Harbor Bay monthly P&L and cash'!F10,"")) -> 0.18147173 | G28: =IF('Harbor Bay monthly P&L and cash'!G26="","",IFERROR('Harbor Bay monthly P&L and cash'!G26/'Harbor Bay monthly P&L and cash'!G10,"")) -> 0.18147173 | H28: =IF('Harbor Bay monthly P&L and cash'!H26="","",IFERROR('Harbor Bay monthly P&L and cash'!H26/'Harbor Bay monthly P&L and cash'!H10,"")) -> 0.18147173 | I28: =IF('Harbor Bay monthly P&L and cash'!I26="","",IFERROR('Harbor Bay monthly P&L and cash'!I26/'Harbor Bay monthly P&L and cash'!I10,"")) -> 0.18147173 | ... P28: =IF('Harbor Bay monthly P&L and cash'!P26="","",IFERROR('Harbor Bay monthly P&L and cash'!P26/'Harbor Bay monthly P&L and cash'!P10,"")) -> 0.18147173
A29: Campaign ROI (proxy, not causal) | B29: =IFERROR(('Harbor Bay monthly P&L and cash'!B15-'Harbor Bay monthly P&L and cash'!B19)/'Harbor Bay monthly P&L and cash'!B19,"") -> 1.5187581 | C29: =IFERROR(('Harbor Bay monthly P&L and cash'!C15-'Harbor Bay monthly P&L and cash'!C19)/'Harbor Bay monthly P&L and cash'!C19,"") -> 1.5187581 | D29: =IFERROR(('Harbor Bay monthly P&L and cash'!D15-'Harbor Bay monthly P&L and cash'!D19)/'Harbor Bay monthly P&L and cash'!D19,"") -> 1.5187581 | E29: =IFERROR(('Harbor Bay monthly P&L and cash'!E15-'Harbor Bay monthly P&L and cash'!E19)/'Harbor Bay monthly P&L and cash'!E19,"") -> 1.5187581 | F29: =IFERROR(('Harbor Bay monthly P&L and cash'!F15-'Harbor Bay monthly P&L and cash'!F19)/'Harbor Bay monthly P&L and cash'!F19,"") -> 1.5187581 | G29: =IFERROR(('Harbor Bay monthly P&L and cash'!G15-'Harbor Bay monthly P&L and cash'!G19)/'Harbor Bay monthly P&L and cash'!G19,"") -> 1.5187581 | H29: =IFERROR(('Harbor Bay monthly P&L and cash'!H15-'Harbor Bay monthly P&L and cash'!H19)/'Harbor Bay monthly P&L and cash'!H19,"") -> 1.5187581 | I29: =IFERROR(('Harbor Bay monthly P&L and cash'!I15-'Harbor Bay monthly P&L and cash'!I19)/'Harbor Bay monthly P&L and cash'!I19,"") -> 1.5187581 | ... P29: =IFERROR(('Harbor Bay monthly P&L and cash'!P15-'Harbor Bay monthly P&L and cash'!P19)/'Harbor Bay monthly P&L and cash'!P19,"") -> 1.5187581
A30: Harbor Bay | B30: =IFERROR(('Harbor Bay monthly P&L and cash'!B16-'Harbor Bay monthly P&L and cash'!B20)/'Harbor Bay monthly P&L and cash'!B20,"") -> 1.5187581 | C30: =IFERROR(('Harbor Bay monthly P&L and cash'!C16-'Harbor Bay monthly P&L and cash'!C20)/'Harbor Bay monthly P&L and cash'!C20,"") -> 1.5187581 | D30: =IFERROR(('Harbor Bay monthly P&L and cash'!D16-'Harbor Bay monthly P&L and cash'!D20)/'Harbor Bay monthly P&L and cash'!D20,"") -> 1.5187581 | E30: =IFERROR(('Harbor Bay monthly P&L and cash'!E16-'Harbor Bay monthly P&L and cash'!E20)/'Harbor Bay monthly P&L and cash'!E20,"") -> 1.5187581 | F30: =IFERROR(('Harbor Bay monthly P&L and cash'!F16-'Harbor Bay monthly P&L and cash'!F20)/'Harbor Bay monthly P&L and cash'!F20,"") -> 1.5187581 | G30: =IFERROR(('Harbor Bay monthly P&L and cash'!G16-'Harbor Bay monthly P&L and cash'!G20)/'Harbor Bay monthly P&L and cash'!G20,"") -> 1.5187581 | H30: =IFERROR(('Harbor Bay monthly P&L and cash'!H16-'Harbor Bay monthly P&L and cash'!H20)/'Harbor Bay monthly P&L and cash'!H20,"") -> 1.5187581 | I30: =IFERROR(('Harbor Bay monthly P&L and cash'!I16-'Harbor Bay monthly P&L and cash'!I20)/'Harbor Bay monthly P&L and cash'!I20,"") -> 1.5187581 | ... P30: =IFERROR(('Harbor Bay monthly P&L and cash'!P16-'Harbor Bay monthly P&L and cash'!P20)/'Harbor Bay monthly P&L and cash'!P20,"") -> 1.5187581
A31: Cash balance | B31: =IF(IF(IF(IFERROR('Harbor Bay assumptions'!B13=""=TRUE,FALSE),TRUE,IF(IFERROR('Harbor Bay monthly P&L and cash'!B25=""=TRUE,FALSE),TRUE,OR('Harbor Bay assumptions'!B13="",'Harbor Bay monthly P&L and cash'!B25="")))="",FALSE,IF(IFERROR('Harbor Bay assumptions'!B13=""=TRUE,FALSE),TRUE,IF(IFERROR('Harbor Bay monthly P&L and cash'!B25=""=TRUE,FALSE),TRUE,OR('Harbor Bay assumptions'!B13="",'Harbor Bay monthly P&L and cash'!B25="")))),"",'Model inputs'!D16+'Harbor Bay monthly P&L and cash'!B25) -> 49281.371 | C31: =IF(IF(IF(IFERROR('Harbor Bay assumptions'!B13=""=TRUE,FALSE),TRUE,IF(IFERROR('Harbor Bay monthly P&L and cash'!C25=""=TRUE,FALSE),TRUE,OR('Harbor Bay assumptions'!B13="",'Harbor Bay monthly P&L and cash'!C25="")))="",FALSE,IF(IFERROR('Harbor Bay assumptions'!B13=""=TRUE,FALSE),TRUE,IF(IFERROR('Harbor Bay monthly P&L and cash'!C25=""=TRUE,FALSE),TRUE,OR('Harbor Bay assumptions'!B13="",'Harbor Bay monthly P&L and cash'!C25="")))),"",'Harbor Bay monthly P&L and cash'!B31+'Harbor Bay monthly P&L and cash'!C25) -> 68562.743 | D31: =IF(IF(IF(IFERROR('Harbor Bay assumptions'!B13=""=TRUE,FALSE),TRUE,IF(IFERROR('Harbor Bay monthly P&L and cash'!D25=""=TRUE,FALSE),TRUE,OR('Harbor Bay assumptions'!B13="",'Harbor Bay monthly P&L and cash'!D25="")))="",FALSE,IF(IFERROR('Harbor Bay assumptions'!B13=""=TRUE,FALSE),TRUE,IF(IFERROR('Harbor Bay monthly P&L and cash'!D25=""=TRUE,FALSE),TRUE,OR('Harbor Bay assumptions'!B13="",'Harbor Bay monthly P&L and cash'!D25="")))),"",'Harbor Bay monthly P&L and cash'!C31+'Harbor Bay monthly P&L and cash'!D25) -> 87844.114 | E31: =IF(IF(IF(IFERROR('Harbor Bay assumptions'!B13=""=TRUE,FALSE),TRUE,IF(IFERROR('Harbor Bay monthly P&L and cash'!E25=""=TRUE,FALSE),TRUE,OR('Harbor Bay assumptions'!B13="",'Harbor Bay monthly P&L and cash'!E25="")))="",FALSE,IF(IFERROR('Harbor Bay assumptions'!B13=""=TRUE,FALSE),TRUE,IF(IFERROR('Harbor Bay monthly P&L and cash'!E25=""=TRUE,FALSE),TRUE,OR('Harbor Bay assumptions'!B13="",'Harbor Bay monthly P&L and cash'!E25="")))),"",'Harbor Bay monthly P&L and cash'!D31+'Harbor Bay monthly P&L and cash'!E25) -> 107125.49 | F31: =IF(IF(IF(IFERROR('Harbor Bay assumptions'!B13=""=TRUE,FALSE),TRUE,IF(IFERROR('Harbor Bay monthly P&L and cash'!F25=""=TRUE,FALSE),TRUE,OR('Harbor Bay assumptions'!B13="",'Harbor Bay monthly P&L and cash'!F25="")))="",FALSE,IF(IFERROR('Harbor Bay assumptions'!B13=""=TRUE,FALSE),TRUE,IF(IFERROR('Harbor Bay monthly P&L and cash'!F25=""=TRUE,FALSE),TRUE,OR('Harbor Bay assumptions'!B13="",'Harbor Bay monthly P&L and cash'!F25="")))),"",'Harbor Bay monthly P&L and cash'!E31+'Harbor Bay monthly P&L and cash'!F25) -> 126406.86 | G31: =IF(IF(IF(IFERROR('Harbor Bay assumptions'!B13=""=TRUE,FALSE),TRUE,IF(IFERROR('Harbor Bay monthly P&L and cash'!G25=""=TRUE,FALSE),TRUE,OR('Harbor Bay assumptions'!B13="",'Harbor Bay monthly P&L and cash'!G25="")))="",FALSE,IF(IFERROR('Harbor Bay assumptions'!B13=""=TRUE,FALSE),TRUE,IF(IFERROR('Harbor Bay monthly P&L and cash'!G25=""=TRUE,FALSE),TRUE,OR('Harbor Bay assumptions'!B13="",'Harbor Bay monthly P&L and cash'!G25="")))),"",'Harbor Bay monthly P&L and cash'!F31+'Harbor Bay monthly P&L and cash'!G25) -> 145688.23 | H31: =IF(IF(IF(IFERROR('Harbor Bay assumptions'!B13=""=TRUE,FALSE),TRUE,IF(IFERROR('Harbor Bay monthly P&L and cash'!H25=""=TRUE,FALSE),TRUE,OR('Harbor Bay assumptions'!B13="",'Harbor Bay monthly P&L and cash'!H25="")))="",FALSE,IF(IFERROR('Harbor Bay assumptions'!B13=""=TRUE,FALSE),TRUE,IF(IFERROR('Harbor Bay monthly P&L and cash'!H25=""=TRUE,FALSE),TRUE,OR('Harbor Bay assumptions'!B13="",'Harbor Bay monthly P&L and cash'!H25="")))),"",'Harbor Bay monthly P&L and cash'!G31+'Harbor Bay monthly P&L and cash'!H25) -> 164969.6 | I31: =IF(IF(IF(IFERROR('Harbor Bay assumptions'!B13=""=TRUE,FALSE),TRUE,IF(IFERROR('Harbor Bay monthly P&L and cash'!I25=""=TRUE,FALSE),TRUE,OR('Harbor Bay assumptions'!B13="",'Harbor Bay monthly P&L and cash'!I25="")))="",FALSE,IF(IFERROR('Harbor Bay assumptions'!B13=""=TRUE,FALSE),TRUE,IF(IFERROR('Harbor Bay monthly P&L and cash'!I25=""=TRUE,FALSE),TRUE,OR('Harbor Bay assumptions'!B13="",'Harbor Bay monthly P&L and cash'!I25="")))),"",'Harbor Bay monthly P&L and cash'!H31+'Harbor Bay monthly P&L and cash'!I25) -> 184250.97 | J31: =IF(IF(IF(IFERROR('Harbor Bay assumptions'!B13=""=TRUE,FALSE),TRUE,IF(IFERROR('Harbor Bay monthly P&L and cash'!J25=""=TRUE,FALSE),TRUE,OR('Harbor Bay assumptions'!B13="",'Harbor Bay monthly P&L and cash'!J25="")))="",FALSE,IF(IFERROR('Harbor Bay assumptions'!B13=""=TRUE,FALSE),TRUE,IF(IFERROR('Harbor Bay monthly P&L and cash'!J25=""=TRUE,FALSE),TRUE,OR('Harbor Bay assumptions'!B13="",'Harbor Bay monthly P&L and cash'!J25="")))),"",'Harbor Bay monthly P&L and cash'!I31+'Harbor Bay monthly P&L and cash'!J25) -> 203532.34 | K31: =IF(IF(IF(IFERROR('Harbor Bay assumptions'!B13=""=TRUE,FALSE),TRUE,IF(IFERROR('Harbor Bay monthly P&L and cash'!K25=""=TRUE,FALSE),TRUE,OR('Harbor Bay assumptions'!B13="",'Harbor Bay monthly P&L and cash'!K25="")))="",FALSE,IF(IFERROR('Harbor Bay assumptions'!B13=""=TRUE,FALSE),TRUE,IF(IFERROR('Harbor Bay monthly P&L and cash'!K25=""=TRUE,FALSE),TRUE,OR('Harbor Bay assumptions'!B13="",'Harbor Bay monthly P&L and cash'!K25="")))),"",'Harbor Bay monthly P&L and cash'!J31+'Harbor Bay monthly P&L and cash'!K25) -> 222813.71 | L31: =IF(IF(IF(IFERROR('Harbor Bay assumptions'!B13=""=TRUE,FALSE),TRUE,IF(IFERROR('Harbor Bay monthly P&L and cash'!L25=""=TRUE,FALSE),TRUE,OR('Harbor Bay assumptions'!B13="",'Harbor Bay monthly P&L and cash'!L25="")))="",FALSE,IF(IFERROR('Harbor Bay assumptions'!B13=""=TRUE,FALSE),TRUE,IF(IFERROR('Harbor Bay monthly P&L and cash'!L25=""=TRUE,FALSE),TRUE,OR('Harbor Bay assumptions'!B13="",'Harbor Bay monthly P&L and cash'!L25="")))),"",'Harbor Bay monthly P&L and cash'!K31+'Harbor Bay monthly P&L and cash'!L25) -> 242095.08 | M31: =IF(IF(IF(IFERROR('Harbor Bay assumptions'!B13=""=TRUE,FALSE),TRUE,IF(IFERROR('Harbor Bay monthly P&L and cash'!M25=""=TRUE,FALSE),TRUE,OR('Harbor Bay assumptions'!B13="",'Harbor Bay monthly P&L and cash'!M25="")))="",FALSE,IF(IFERROR('Harbor Bay assumptions'!B13=""=TRUE,FALSE),TRUE,IF(IFERROR('Harbor Bay monthly P&L and cash'!M25=""=TRUE,FALSE),TRUE,OR('Harbor Bay assumptions'!B13="",'Harbor Bay monthly P&L and cash'!M25="")))),"",'Harbor Bay monthly P&L and cash'!L31+'Harbor Bay monthly P&L and cash'!M25) -> 261376.46 | N31: =IF(IF(IF(IFERROR('Harbor Bay assumptions'!B13=""=TRUE,FALSE),TRUE,IF(IFERROR('Harbor Bay monthly P&L and cash'!N25=""=TRUE,FALSE),TRUE,OR('Harbor Bay assumptions'!B13="",'Harbor Bay monthly P&L and cash'!N25="")))="",FALSE,IF(IFERROR('Harbor Bay assumptions'!B13=""=TRUE,FALSE),TRUE,IF(IFERROR('Harbor Bay monthly P&L and cash'!N25=""=TRUE,FALSE),TRUE,OR('Harbor Bay assumptions'!B13="",'Harbor Bay monthly P&L and cash'!N25="")))),"",'Harbor Bay monthly P&L and cash'!M31+'Harbor Bay monthly P&L and cash'!N25) -> 280657.83 | O31: =IF(IF(IF(IFERROR('Harbor Bay assumptions'!B13=""=TRUE,FALSE),TRUE,IF(IFERROR('Harbor Bay monthly P&L and cash'!O25=""=TRUE,FALSE),TRUE,OR('Harbor Bay assumptions'!B13="",'Harbor Bay monthly P&L and cash'!O25="")))="",FALSE,IF(IFERROR('Harbor Bay assumptions'!B13=""=TRUE,FALSE),TRUE,IF(IFERROR('Harbor Bay monthly P&L and cash'!O25=""=TRUE,FALSE),TRUE,OR('Harbor Bay assumptions'!B13="",'Harbor Bay monthly P&L and cash'!O25="")))),"",'Harbor Bay monthly P&L and cash'!N31+'Harbor Bay monthly P&L and cash'!O25) -> 299939.2 | P31: =IF(IF(IF(IFERROR('Harbor Bay assumptions'!B13=""=TRUE,FALSE),TRUE,IF(IFERROR('Harbor Bay monthly P&L and cash'!P25=""=TRUE,FALSE),TRUE,OR('Harbor Bay assumptions'!B13="",'Harbor Bay monthly P&L and cash'!P25="")))="",FALSE,IF(IFERROR('Harbor Bay assumptions'!B13=""=TRUE,FALSE),TRUE,IF(IFERROR('Harbor Bay monthly P&L and cash'!P25=""=TRUE,FALSE),TRUE,OR('Harbor Bay assumptions'!B13="",'Harbor Bay monthly P&L and cash'!P25="")))),"",'Harbor Bay monthly P&L and cash'!O31+'Harbor Bay monthly P&L and cash'!P25) -> 319220.57
A32: Harbor Bay | B32: =IF(IF(IF(IFERROR('Harbor Bay assumptions'!B13=""=TRUE,FALSE),TRUE,IF(IFERROR('Harbor Bay monthly P&L and cash'!B26=""=TRUE,FALSE),TRUE,OR('Harbor Bay assumptions'!B13="",'Harbor Bay monthly P&L and cash'!B26="")))="",FALSE,IF(IFERROR('Harbor Bay assumptions'!B13=""=TRUE,FALSE),TRUE,IF(IFERROR('Harbor Bay monthly P&L and cash'!B26=""=TRUE,FALSE),TRUE,OR('Harbor Bay assumptions'!B13="",'Harbor Bay monthly P&L and cash'!B26="")))),"",'Model inputs'!D17+'Harbor Bay monthly P&L and cash'!B26) -> 49281.371 | C32: =IF(IF(IF(IFERROR('Harbor Bay assumptions'!B13=""=TRUE,FALSE),TRUE,IF(IFERROR('Harbor Bay monthly P&L and cash'!C26=""=TRUE,FALSE),TRUE,OR('Harbor Bay assumptions'!B13="",'Harbor Bay monthly P&L and cash'!C26="")))="",FALSE,IF(IFERROR('Harbor Bay assumptions'!B13=""=TRUE,FALSE),TRUE,IF(IFERROR('Harbor Bay monthly P&L and cash'!C26=""=TRUE,FALSE),TRUE,OR('Harbor Bay assumptions'!B13="",'Harbor Bay monthly P&L and cash'!C26="")))),"",'Harbor Bay monthly P&L and cash'!B32+'Harbor Bay monthly P&L and cash'!C26) -> 68562.743 | D32: =IF(IF(IF(IFERROR('Harbor Bay assumptions'!B13=""=TRUE,FALSE),TRUE,IF(IFERROR('Harbor Bay monthly P&L and cash'!D26=""=TRUE,FALSE),TRUE,OR('Harbor Bay assumptions'!B13="",'Harbor Bay monthly P&L and cash'!D26="")))="",FALSE,IF(IFERROR('Harbor Bay assumptions'!B13=""=TRUE,FALSE),TRUE,IF(IFERROR('Harbor Bay monthly P&L and cash'!D26=""=TRUE,FALSE),TRUE,OR('Harbor Bay assumptions'!B13="",'Harbor Bay monthly P&L and cash'!D26="")))),"",'Harbor Bay monthly P&L and cash'!C32+'Harbor Bay monthly P&L and cash'!D26) -> 87844.114 | E32: =IF(IF(IF(IFERROR('Harbor Bay assumptions'!B13=""=TRUE,FALSE),TRUE,IF(IFERROR('Harbor Bay monthly P&L and cash'!E26=""=TRUE,FALSE),TRUE,OR('Harbor Bay assumptions'!B13="",'Harbor Bay monthly P&L and cash'!E26="")))="",FALSE,IF(IFERROR('Harbor Bay assumptions'!B13=""=TRUE,FALSE),TRUE,IF(IFERROR('Harbor Bay monthly P&L and cash'!E26=""=TRUE,FALSE),TRUE,OR('Harbor Bay assumptions'!B13="",'Harbor Bay monthly P&L and cash'!E26="")))),"",'Harbor Bay monthly P&L and cash'!D32+'Harbor Bay monthly P&L and cash'!E26) -> 107125.49 | F32: =IF(IF(IF(IFERROR('Harbor Bay assumptions'!B13=""=TRUE,FALSE),TRUE,IF(IFERROR('Harbor Bay monthly P&L and cash'!F26=""=TRUE,FALSE),TRUE,OR('Harbor Bay assumptions'!B13="",'Harbor Bay monthly P&L and cash'!F26="")))="",FALSE,IF(IFERROR('Harbor Bay assumptions'!B13=""=TRUE,FALSE),TRUE,IF(IFERROR('Harbor Bay monthly P&L and cash'!F26=""=TRUE,FALSE),TRUE,OR('Harbor Bay assumptions'!B13="",'Harbor Bay monthly P&L and cash'!F26="")))),"",'Harbor Bay monthly P&L and cash'!E32+'Harbor Bay monthly P&L and cash'!F26) -> 126406.86 | G32: =IF(IF(IF(IFERROR('Harbor Bay assumptions'!B13=""=TRUE,FALSE),TRUE,IF(IFERROR('Harbor Bay monthly P&L and cash'!G26=""=TRUE,FALSE),TRUE,OR('Harbor Bay assumptions'!B13="",'Harbor Bay monthly P&L and cash'!G26="")))="",FALSE,IF(IFERROR('Harbor Bay assumptions'!B13=""=TRUE,FALSE),TRUE,IF(IFERROR('Harbor Bay monthly P&L and cash'!G26=""=TRUE,FALSE),TRUE,OR('Harbor Bay assumptions'!B13="",'Harbor Bay monthly P&L and cash'!G26="")))),"",'Harbor Bay monthly P&L and cash'!F32+'Harbor Bay monthly P&L and cash'!G26) -> 145688.23 | H32: =IF(IF(IF(IFERROR('Harbor Bay assumptions'!B13=""=TRUE,FALSE),TRUE,IF(IFERROR('Harbor Bay monthly P&L and cash'!H26=""=TRUE,FALSE),TRUE,OR('Harbor Bay assumptions'!B13="",'Harbor Bay monthly P&L and cash'!H26="")))="",FALSE,IF(IFERROR('Harbor Bay assumptions'!B13=""=TRUE,FALSE),TRUE,IF(IFERROR('Harbor Bay monthly P&L and cash'!H26=""=TRUE,FALSE),TRUE,OR('Harbor Bay assumptions'!B13="",'Harbor Bay monthly P&L and cash'!H26="")))),"",'Harbor Bay monthly P&L and cash'!G32+'Harbor Bay monthly P&L and cash'!H26) -> 164969.6 | I32: =IF(IF(IF(IFERROR('Harbor Bay assumptions'!B13=""=TRUE,FALSE),TRUE,IF(IFERROR('Harbor Bay monthly P&L and cash'!I26=""=TRUE,FALSE),TRUE,OR('Harbor Bay assumptions'!B13="",'Harbor Bay monthly P&L and cash'!I26="")))="",FALSE,IF(IFERROR('Harbor Bay assumptions'!B13=""=TRUE,FALSE),TRUE,IF(IFERROR('Harbor Bay monthly P&L and cash'!I26=""=TRUE,FALSE),TRUE,OR('Harbor Bay assumptions'!B13="",'Harbor Bay monthly P&L and cash'!I26="")))),"",'Harbor Bay monthly P&L and cash'!H32+'Harbor Bay monthly P&L and cash'!I26) -> 184250.97 | J32: =IF(IF(IF(IFERROR('Harbor Bay assumptions'!B13=""=TRUE,FALSE),TRUE,IF(IFERROR('Harbor Bay monthly P&L and cash'!J26=""=TRUE,FALSE),TRUE,OR('Harbor Bay assumptions'!B13="",'Harbor Bay monthly P&L and cash'!J26="")))="",FALSE,IF(IFERROR('Harbor Bay assumptions'!B13=""=TRUE,FALSE),TRUE,IF(IFERROR('Harbor Bay monthly P&L and cash'!J26=""=TRUE,FALSE),TRUE,OR('Harbor Bay assumptions'!B13="",'Harbor Bay monthly P&L and cash'!J26="")))),"",'Harbor Bay monthly P&L and cash'!I32+'Harbor Bay monthly P&L and cash'!J26) -> 203532.34 | K32: =IF(IF(IF(IFERROR('Harbor Bay assumptions'!B13=""=TRUE,FALSE),TRUE,IF(IFERROR('Harbor Bay monthly P&L and cash'!K26=""=TRUE,FALSE),TRUE,OR('Harbor Bay assumptions'!B13="",'Harbor Bay monthly P&L and cash'!K26="")))="",FALSE,IF(IFERROR('Harbor Bay assumptions'!B13=""=TRUE,FALSE),TRUE,IF(IFERROR('Harbor Bay monthly P&L and cash'!K26=""=TRUE,FALSE),TRUE,OR('Harbor Bay assumptions'!B13="",'Harbor Bay monthly P&L and cash'!K26="")))),"",'Harbor Bay monthly P&L and cash'!J32+'Harbor Bay monthly P&L and cash'!K26) -> 222813.71 | L32: =IF(IF(IF(IFERROR('Harbor Bay assumptions'!B13=""=TRUE,FALSE),TRUE,IF(IFERROR('Harbor Bay monthly P&L and cash'!L26=""=TRUE,FALSE),TRUE,OR('Harbor Bay assumptions'!B13="",'Harbor Bay monthly P&L and cash'!L26="")))="",FALSE,IF(IFERROR('Harbor Bay assumptions'!B13=""=TRUE,FALSE),TRUE,IF(IFERROR('Harbor Bay monthly P&L and cash'!L26=""=TRUE,FALSE),TRUE,OR('Harbor Bay assumptions'!B13="",'Harbor Bay monthly P&L and cash'!L26="")))),"",'Harbor Bay monthly P&L and cash'!K32+'Harbor Bay monthly P&L and cash'!L26) -> 242095.08 | M32: =IF(IF(IF(IFERROR('Harbor Bay assumptions'!B13=""=TRUE,FALSE),TRUE,IF(IFERROR('Harbor Bay monthly P&L and cash'!M26=""=TRUE,FALSE),TRUE,OR('Harbor Bay assumptions'!B13="",'Harbor Bay monthly P&L and cash'!M26="")))="",FALSE,IF(IFERROR('Harbor Bay assumptions'!B13=""=TRUE,FALSE),TRUE,IF(IFERROR('Harbor Bay monthly P&L and cash'!M26=""=TRUE,FALSE),TRUE,OR('Harbor Bay assumptions'!B13="",'Harbor Bay monthly P&L and cash'!M26="")))),"",'Harbor Bay monthly P&L and cash'!L32+'Harbor Bay monthly P&L and cash'!M26) -> 261376.46 | N32: =IF(IF(IF(IFERROR('Harbor Bay assumptions'!B13=""=TRUE,FALSE),TRUE,IF(IFERROR('Harbor Bay monthly P&L and cash'!N26=""=TRUE,FALSE),TRUE,OR('Harbor Bay assumptions'!B13="",'Harbor Bay monthly P&L and cash'!N26="")))="",FALSE,IF(IFERROR('Harbor Bay assumptions'!B13=""=TRUE,FALSE),TRUE,IF(IFERROR('Harbor Bay monthly P&L and cash'!N26=""=TRUE,FALSE),TRUE,OR('Harbor Bay assumptions'!B13="",'Harbor Bay monthly P&L and cash'!N26="")))),"",'Harbor Bay monthly P&L and cash'!M32+'Harbor Bay monthly P&L and cash'!N26) -> 280657.83 | O32: =IF(IF(IF(IFERROR('Harbor Bay assumptions'!B13=""=TRUE,FALSE),TRUE,IF(IFERROR('Harbor Bay monthly P&L and cash'!O26=""=TRUE,FALSE),TRUE,OR('Harbor Bay assumptions'!B13="",'Harbor Bay monthly P&L and cash'!O26="")))="",FALSE,IF(IFERROR('Harbor Bay assumptions'!B13=""=TRUE,FALSE),TRUE,IF(IFERROR('Harbor Bay monthly P&L and cash'!O26=""=TRUE,FALSE),TRUE,OR('Harbor Bay assumptions'!B13="",'Harbor Bay monthly P&L and cash'!O26="")))),"",'Harbor Bay monthly P&L and cash'!N32+'Harbor Bay monthly P&L and cash'!O26) -> 299939.2 | P32: =IF(IF(IF(IFERROR('Harbor Bay assumptions'!B13=""=TRUE,FALSE),TRUE,IF(IFERROR('Harbor Bay monthly P&L and cash'!P26=""=TRUE,FALSE),TRUE,OR('Harbor Bay assumptions'!B13="",'Harbor Bay monthly P&L and cash'!P26="")))="",FALSE,IF(IFERROR('Harbor Bay assumptions'!B13=""=TRUE,FALSE),TRUE,IF(IFERROR('Harbor Bay monthly P&L and cash'!P26=""=TRUE,FALSE),TRUE,OR('Harbor Bay assumptions'!B13="",'Harbor Bay monthly P&L and cash'!P26="")))),"",'Harbor Bay monthly P&L and cash'!O32+'Harbor Bay monthly P&L and cash'!P26) -> 319220.57
A33: Runway (months, loss cases only) | B33: =IF(IF(IF(IFERROR('Harbor Bay monthly P&L and cash'!B25=""=TRUE,FALSE),TRUE,IF(IFERROR('Harbor Bay monthly P&L and cash'!B31=""=TRUE,FALSE),TRUE,OR('Harbor Bay monthly P&L and cash'!B25="",'Harbor Bay monthly P&L and cash'!B31="")))="",FALSE,IF(IFERROR('Harbor Bay monthly P&L and cash'!B25=""=TRUE,FALSE),TRUE,IF(IFERROR('Harbor Bay monthly P&L and cash'!B31=""=TRUE,FALSE),TRUE,OR('Harbor Bay monthly P&L and cash'!B25="",'Harbor Bay monthly P&L and cash'!B31="")))),"",IFERROR(IF(IF(IF(ISERROR('Harbor Bay monthly P&L and cash'!B25<0),'Harbor Bay monthly P&L and cash'!B25<0,IF('Harbor Bay monthly P&L and cash'!B25="","",'Harbor Bay monthly P&L and cash'!B25<0))="",FALSE,IF(ISERROR('Harbor Bay monthly P&L and cash'!B25<0),'Harbor Bay monthly P&L and cash'!B25<0,IF('Harbor Bay monthly P&L and cash'!B25="","",'Harbor Bay monthly P&L and cash'!B25<0))),MAX('Harbor Bay monthly P&L and cash'!B31/(0-'Harbor Bay monthly P&L and cash'!B25),0),""),"")) | C33: =IF(IF(IF(IFERROR('Harbor Bay monthly P&L and cash'!C25=""=TRUE,FALSE),TRUE,IF(IFERROR('Harbor Bay monthly P&L and cash'!C31=""=TRUE,FALSE),TRUE,OR('Harbor Bay monthly P&L and cash'!C25="",'Harbor Bay monthly P&L and cash'!C31="")))="",FALSE,IF(IFERROR('Harbor Bay monthly P&L and cash'!C25=""=TRUE,FALSE),TRUE,IF(IFERROR('Harbor Bay monthly P&L and cash'!C31=""=TRUE,FALSE),TRUE,OR('Harbor Bay monthly P&L and cash'!C25="",'Harbor Bay monthly P&L and cash'!C31="")))),"",IFERROR(IF(IF(IF(ISERROR('Harbor Bay monthly P&L and cash'!C25<0),'Harbor Bay monthly P&L and cash'!C25<0,IF('Harbor Bay monthly P&L and cash'!C25="","",'Harbor Bay monthly P&L and cash'!C25<0))="",FALSE,IF(ISERROR('Harbor Bay monthly P&L and cash'!C25<0),'Harbor Bay monthly P&L and cash'!C25<0,IF('Harbor Bay monthly P&L and cash'!C25="","",'Harbor Bay monthly P&L and cash'!C25<0))),MAX('Harbor Bay monthly P&L and cash'!C31/(0-'Harbor Bay monthly P&L and cash'!C25),0),""),"")) | D33: =IF(IF(IF(IFERROR('Harbor Bay monthly P&L and cash'!D25=""=TRUE,FALSE),TRUE,IF(IFERROR('Harbor Bay monthly P&L and cash'!D31=""=TRUE,FALSE),TRUE,OR('Harbor Bay monthly P&L and cash'!D25="",'Harbor Bay monthly P&L and cash'!D31="")))="",FALSE,IF(IFERROR('Harbor Bay monthly P&L and cash'!D25=""=TRUE,FALSE),TRUE,IF(IFERROR('Harbor Bay monthly P&L and cash'!D31=""=TRUE,FALSE),TRUE,OR('Harbor Bay monthly P&L and cash'!D25="",'Harbor Bay monthly P&L and cash'!D31="")))),"",IFERROR(IF(IF(IF(ISERROR('Harbor Bay monthly P&L and cash'!D25<0),'Harbor Bay monthly P&L and cash'!D25<0,IF('Harbor Bay monthly P&L and cash'!D25="","",'Harbor Bay monthly P&L and cash'!D25<0))="",FALSE,IF(ISERROR('Harbor Bay monthly P&L and cash'!D25<0),'Harbor Bay monthly P&L and cash'!D25<0,IF('Harbor Bay monthly P&L and cash'!D25="","",'Harbor Bay monthly P&L and cash'!D25<0))),MAX('Harbor Bay monthly P&L and cash'!D31/(0-'Harbor Bay monthly P&L and cash'!D25),0),""),"")) | E33: =IF(IF(IF(IFERROR('Harbor Bay monthly P&L and cash'!E25=""=TRUE,FALSE),TRUE,IF(IFERROR('Harbor Bay monthly P&L and cash'!E31=""=TRUE,FALSE),TRUE,OR('Harbor Bay monthly P&L and cash'!E25="",'Harbor Bay monthly P&L and cash'!E31="")))="",FALSE,IF(IFERROR('Harbor Bay monthly P&L and cash'!E25=""=TRUE,FALSE),TRUE,IF(IFERROR('Harbor Bay monthly P&L and cash'!E31=""=TRUE,FALSE),TRUE,OR('Harbor Bay monthly P&L and cash'!E25="",'Harbor Bay monthly P&L and cash'!E31="")))),"",IFERROR(IF(IF(IF(ISERROR('Harbor Bay monthly P&L and cash'!E25<0),'Harbor Bay monthly P&L and cash'!E25<0,IF('Harbor Bay monthly P&L and cash'!E25="","",'Harbor Bay monthly P&L and cash'!E25<0))="",FALSE,IF(ISERROR('Harbor Bay monthly P&L and cash'!E25<0),'Harbor Bay monthly P&L and cash'!E25<0,IF('Harbor Bay monthly P&L and cash'!E25="","",'Harbor Bay monthly P&L and cash'!E25<0))),MAX('Harbor Bay monthly P&L and cash'!E31/(0-'Harbor Bay monthly P&L and cash'!E25),0),""),"")) | F33: =IF(IF(IF(IFERROR('Harbor Bay monthly P&L and cash'!F25=""=TRUE,FALSE),TRUE,IF(IFERROR('Harbor Bay monthly P&L and cash'!F31=""=TRUE,FALSE),TRUE,OR('Harbor Bay monthly P&L and cash'!F25="",'Harbor Bay monthly P&L and cash'!F31="")))="",FALSE,IF(IFERROR('Harbor Bay monthly P&L and cash'!F25=""=TRUE,FALSE),TRUE,IF(IFERROR('Harbor Bay monthly P&L and cash'!F31=""=TRUE,FALSE),TRUE,OR('Harbor Bay monthly P&L and cash'!F25="",'Harbor Bay monthly P&L and cash'!F31="")))),"",IFERROR(IF(IF(IF(ISERROR('Harbor Bay monthly P&L and cash'!F25<0),'Harbor Bay monthly P&L and cash'!F25<0,IF('Harbor Bay monthly P&L and cash'!F25="","",'Harbor Bay monthly P&L and cash'!F25<0))="",FALSE,IF(ISERROR('Harbor Bay monthly P&L and cash'!F25<0),'Harbor Bay monthly P&L and cash'!F25<0,IF('Harbor Bay monthly P&L and cash'!F25="","",'Harbor Bay monthly P&L and cash'!F25<0))),MAX('Harbor Bay monthly P&L and cash'!F31/(0-'Harbor Bay monthly P&L and cash'!F25),0),""),"")) | G33: =IF(IF(IF(IFERROR('Harbor Bay monthly P&L and cash'!G25=""=TRUE,FALSE),TRUE,IF(IFERROR('Harbor Bay monthly P&L and cash'!G31=""=TRUE,FALSE),TRUE,OR('Harbor Bay monthly P&L and cash'!G25="",'Harbor Bay monthly P&L and cash'!G31="")))="",FALSE,IF(IFERROR('Harbor Bay monthly P&L and cash'!G25=""=TRUE,FALSE),TRUE,IF(IFERROR('Harbor Bay monthly P&L and cash'!G31=""=TRUE,FALSE),TRUE,OR('Harbor Bay monthly P&L and cash'!G25="",'Harbor Bay monthly P&L and cash'!G31="")))),"",IFERROR(IF(IF(IF(ISERROR('Harbor Bay monthly P&L and cash'!G25<0),'Harbor Bay monthly P&L and cash'!G25<0,IF('Harbor Bay monthly P&L and cash'!G25="","",'Harbor Bay monthly P&L and cash'!G25<0))="",FALSE,IF(ISERROR('Harbor Bay monthly P&L and cash'!G25<0),'Harbor Bay monthly P&L and cash'!G25<0,IF('Harbor Bay monthly P&L and cash'!G25="","",'Harbor Bay monthly P&L and cash'!G25<0))),MAX('Harbor Bay monthly P&L and cash'!G31/(0-'Harbor Bay monthly P&L and cash'!G25),0),""),"")) | H33: =IF(IF(IF(IFERROR('Harbor Bay monthly P&L and cash'!H25=""=TRUE,FALSE),TRUE,IF(IFERROR('Harbor Bay monthly P&L and cash'!H31=""=TRUE,FALSE),TRUE,OR('Harbor Bay monthly P&L and cash'!H25="",'Harbor Bay monthly P&L and cash'!H31="")))="",FALSE,IF(IFERROR('Harbor Bay monthly P&L and cash'!H25=""=TRUE,FALSE),TRUE,IF(IFERROR('Harbor Bay monthly P&L and cash'!H31=""=TRUE,FALSE),TRUE,OR('Harbor Bay monthly P&L and cash'!H25="",'Harbor Bay monthly P&L and cash'!H31="")))),"",IFERROR(IF(IF(IF(ISERROR('Harbor Bay monthly P&L and cash'!H25<0),'Harbor Bay monthly P&L and cash'!H25<0,IF('Harbor Bay monthly P&L and cash'!H25="","",'Harbor Bay monthly P&L and cash'!H25<0))="",FALSE,IF(ISERROR('Harbor Bay monthly P&L and cash'!H25<0),'Harbor Bay monthly P&L and cash'!H25<0,IF('Harbor Bay monthly P&L and cash'!H25="","",'Harbor Bay monthly P&L and cash'!H25<0))),MAX('Harbor Bay monthly P&L and cash'!H31/(0-'Harbor Bay monthly P&L and cash'!H25),0),""),"")) | I33: =IF(IF(IF(IFERROR('Harbor Bay monthly P&L and cash'!I25=""=TRUE,FALSE),TRUE,IF(IFERROR('Harbor Bay monthly P&L and cash'!I31=""=TRUE,FALSE),TRUE,OR('Harbor Bay monthly P&L and cash'!I25="",'Harbor Bay monthly P&L and cash'!I31="")))="",FALSE,IF(IFERROR('Harbor Bay monthly P&L and cash'!I25=""=TRUE,FALSE),TRUE,IF(IFERROR('Harbor Bay monthly P&L and cash'!I31=""=TRUE,FALSE),TRUE,OR('Harbor Bay monthly P&L and cash'!I25="",'Harbor Bay monthly P&L and cash'!I31="")))),"",IFERROR(IF(IF(IF(ISERROR('Harbor Bay monthly P&L and cash'!I25<0),'Harbor Bay monthly P&L and cash'!I25<0,IF('Harbor Bay monthly P&L and cash'!I25="","",'Harbor Bay monthly P&L and cash'!I25<0))="",FALSE,IF(ISERROR('Harbor Bay monthly P&L and cash'!I25<0),'Harbor Bay monthly P&L and cash'!I25<0,IF('Harbor Bay monthly P&L and cash'!I25="","",'Harbor Bay monthly P&L and cash'!I25<0))),MAX('Harbor Bay monthly P&L and cash'!I31/(0-'Harbor Bay monthly P&L and cash'!I25),0),""),"")) | ... P33: =IF(IF(IF(IFERROR('Harbor Bay monthly P&L and cash'!P25=""=TRUE,FALSE),TRUE,IF(IFERROR('Harbor Bay monthly P&L and cash'!P31=""=TRUE,FALSE),TRUE,OR('Harbor Bay monthly P&L and cash'!P25="",'Harbor Bay monthly P&L and cash'!P31="")))="",FALSE,IF(IFERROR('Harbor Bay monthly P&L and cash'!P25=""=TRUE,FALSE),TRUE,IF(IFERROR('Harbor Bay monthly P&L and cash'!P31=""=TRUE,FALSE),TRUE,OR('Harbor Bay monthly P&L and cash'!P25="",'Harbor Bay monthly P&L and cash'!P31="")))),"",IFERROR(IF(IF(IF(ISERROR('Harbor Bay monthly P&L and cash'!P25<0),'Harbor Bay monthly P&L and cash'!P25<0,IF('Harbor Bay monthly P&L and cash'!P25="","",'Harbor Bay monthly P&L and cash'!P25<0))="",FALSE,IF(ISERROR('Harbor Bay monthly P&L and cash'!P25<0),'Harbor Bay monthly P&L and cash'!P25<0,IF('Harbor Bay monthly P&L and cash'!P25="","",'Harbor Bay monthly P&L and cash'!P25<0))),MAX('Harbor Bay monthly P&L and cash'!P31/(0-'Harbor Bay monthly P&L and cash'!P25),0),""),""))
A34: Harbor Bay | B34: =IF(IF(IF(IFERROR('Harbor Bay monthly P&L and cash'!B26=""=TRUE,FALSE),TRUE,IF(IFERROR('Harbor Bay monthly P&L and cash'!B32=""=TRUE,FALSE),TRUE,OR('Harbor Bay monthly P&L and cash'!B26="",'Harbor Bay monthly P&L and cash'!B32="")))="",FALSE,IF(IFERROR('Harbor Bay monthly P&L and cash'!B26=""=TRUE,FALSE),TRUE,IF(IFERROR('Harbor Bay monthly P&L and cash'!B32=""=TRUE,FALSE),TRUE,OR('Harbor Bay monthly P&L and cash'!B26="",'Harbor Bay monthly P&L and cash'!B32="")))),"",IFERROR(IF(IF(IF(ISERROR('Harbor Bay monthly P&L and cash'!B26<0),'Harbor Bay monthly P&L and cash'!B26<0,IF('Harbor Bay monthly P&L and cash'!B26="","",'Harbor Bay monthly P&L and cash'!B26<0))="",FALSE,IF(ISERROR('Harbor Bay monthly P&L and cash'!B26<0),'Harbor Bay monthly P&L and cash'!B26<0,IF('Harbor Bay monthly P&L and cash'!B26="","",'Harbor Bay monthly P&L and cash'!B26<0))),MAX('Harbor Bay monthly P&L and cash'!B32/(0-'Harbor Bay monthly P&L and cash'!B26),0),""),"")) | C34: =IF(IF(IF(IFERROR('Harbor Bay monthly P&L and cash'!C26=""=TRUE,FALSE),TRUE,IF(IFERROR('Harbor Bay monthly P&L and cash'!C32=""=TRUE,FALSE),TRUE,OR('Harbor Bay monthly P&L and cash'!C26="",'Harbor Bay monthly P&L and cash'!C32="")))="",FALSE,IF(IFERROR('Harbor Bay monthly P&L and cash'!C26=""=TRUE,FALSE),TRUE,IF(IFERROR('Harbor Bay monthly P&L and cash'!C32=""=TRUE,FALSE),TRUE,OR('Harbor Bay monthly P&L and cash'!C26="",'Harbor Bay monthly P&L and cash'!C32="")))),"",IFERROR(IF(IF(IF(ISERROR('Harbor Bay monthly P&L and cash'!C26<0),'Harbor Bay monthly P&L and cash'!C26<0,IF('Harbor Bay monthly P&L and cash'!C26="","",'Harbor Bay monthly P&L and cash'!C26<0))="",FALSE,IF(ISERROR('Harbor Bay monthly P&L and cash'!C26<0),'Harbor Bay monthly P&L and cash'!C26<0,IF('Harbor Bay monthly P&L and cash'!C26="","",'Harbor Bay monthly P&L and cash'!C26<0))),MAX('Harbor Bay monthly P&L and cash'!C32/(0-'Harbor Bay monthly P&L and cash'!C26),0),""),"")) | D34: =IF(IF(IF(IFERROR('Harbor Bay monthly P&L and cash'!D26=""=TRUE,FALSE),TRUE,IF(IFERROR('Harbor Bay monthly P&L and cash'!D32=""=TRUE,FALSE),TRUE,OR('Harbor Bay monthly P&L and cash'!D26="",'Harbor Bay monthly P&L and cash'!D32="")))="",FALSE,IF(IFERROR('Harbor Bay monthly P&L and cash'!D26=""=TRUE,FALSE),TRUE,IF(IFERROR('Harbor Bay monthly P&L and cash'!D32=""=TRUE,FALSE),TRUE,OR('Harbor Bay monthly P&L and cash'!D26="",'Harbor Bay monthly P&L and cash'!D32="")))),"",IFERROR(IF(IF(IF(ISERROR('Harbor Bay monthly P&L and cash'!D26<0),'Harbor Bay monthly P&L and cash'!D26<0,IF('Harbor Bay monthly P&L and cash'!D26="","",'Harbor Bay monthly P&L and cash'!D26<0))="",FALSE,IF(ISERROR('Harbor Bay monthly P&L and cash'!D26<0),'Harbor Bay monthly P&L and cash'!D26<0,IF('Harbor Bay monthly P&L and cash'!D26="","",'Harbor Bay monthly P&L and cash'!D26<0))),MAX('Harbor Bay monthly P&L and cash'!D32/(0-'Harbor Bay monthly P&L and cash'!D26),0),""),"")) | E34: =IF(IF(IF(IFERROR('Harbor Bay monthly P&L and cash'!E26=""=TRUE,FALSE),TRUE,IF(IFERROR('Harbor Bay monthly P&L and cash'!E32=""=TRUE,FALSE),TRUE,OR('Harbor Bay monthly P&L and cash'!E26="",'Harbor Bay monthly P&L and cash'!E32="")))="",FALSE,IF(IFERROR('Harbor Bay monthly P&L and cash'!E26=""=TRUE,FALSE),TRUE,IF(IFERROR('Harbor Bay monthly P&L and cash'!E32=""=TRUE,FALSE),TRUE,OR('Harbor Bay monthly P&L and cash'!E26="",'Harbor Bay monthly P&L and cash'!E32="")))),"",IFERROR(IF(IF(IF(ISERROR('Harbor Bay monthly P&L and cash'!E26<0),'Harbor Bay monthly P&L and cash'!E26<0,IF('Harbor Bay monthly P&L and cash'!E26="","",'Harbor Bay monthly P&L and cash'!E26<0))="",FALSE,IF(ISERROR('Harbor Bay monthly P&L and cash'!E26<0),'Harbor Bay monthly P&L and cash'!E26<0,IF('Harbor Bay monthly P&L and cash'!E26="","",'Harbor Bay monthly P&L and cash'!E26<0))),MAX('Harbor Bay monthly P&L and cash'!E32/(0-'Harbor Bay monthly P&L and cash'!E26),0),""),"")) | F34: =IF(IF(IF(IFERROR('Harbor Bay monthly P&L and cash'!F26=""=TRUE,FALSE),TRUE,IF(IFERROR('Harbor Bay monthly P&L and cash'!F32=""=TRUE,FALSE),TRUE,OR('Harbor Bay monthly P&L and cash'!F26="",'Harbor Bay monthly P&L and cash'!F32="")))="",FALSE,IF(IFERROR('Harbor Bay monthly P&L and cash'!F26=""=TRUE,FALSE),TRUE,IF(IFERROR('Harbor Bay monthly P&L and cash'!F32=""=TRUE,FALSE),TRUE,OR('Harbor Bay monthly P&L and cash'!F26="",'Harbor Bay monthly P&L and cash'!F32="")))),"",IFERROR(IF(IF(IF(ISERROR('Harbor Bay monthly P&L and cash'!F26<0),'Harbor Bay monthly P&L and cash'!F26<0,IF('Harbor Bay monthly P&L and cash'!F26="","",'Harbor Bay monthly P&L and cash'!F26<0))="",FALSE,IF(ISERROR('Harbor Bay monthly P&L and cash'!F26<0),'Harbor Bay monthly P&L and cash'!F26<0,IF('Harbor Bay monthly P&L and cash'!F26="","",'Harbor Bay monthly P&L and cash'!F26<0))),MAX('Harbor Bay monthly P&L and cash'!F32/(0-'Harbor Bay monthly P&L and cash'!F26),0),""),"")) | G34: =IF(IF(IF(IFERROR('Harbor Bay monthly P&L and cash'!G26=""=TRUE,FALSE),TRUE,IF(IFERROR('Harbor Bay monthly P&L and cash'!G32=""=TRUE,FALSE),TRUE,OR('Harbor Bay monthly P&L and cash'!G26="",'Harbor Bay monthly P&L and cash'!G32="")))="",FALSE,IF(IFERROR('Harbor Bay monthly P&L and cash'!G26=""=TRUE,FALSE),TRUE,IF(IFERROR('Harbor Bay monthly P&L and cash'!G32=""=TRUE,FALSE),TRUE,OR('Harbor Bay monthly P&L and cash'!G26="",'Harbor Bay monthly P&L and cash'!G32="")))),"",IFERROR(IF(IF(IF(ISERROR('Harbor Bay monthly P&L and cash'!G26<0),'Harbor Bay monthly P&L and cash'!G26<0,IF('Harbor Bay monthly P&L and cash'!G26="","",'Harbor Bay monthly P&L and cash'!G26<0))="",FALSE,IF(ISERROR('Harbor Bay monthly P&L and cash'!G26<0),'Harbor Bay monthly P&L and cash'!G26<0,IF('Harbor Bay monthly P&L and cash'!G26="","",'Harbor Bay monthly P&L and cash'!G26<0))),MAX('Harbor Bay monthly P&L and cash'!G32/(0-'Harbor Bay monthly P&L and cash'!G26),0),""),"")) | H34: =IF(IF(IF(IFERROR('Harbor Bay monthly P&L and cash'!H26=""=TRUE,FALSE),TRUE,IF(IFERROR('Harbor Bay monthly P&L and cash'!H32=""=TRUE,FALSE),TRUE,OR('Harbor Bay monthly P&L and cash'!H26="",'Harbor Bay monthly P&L and cash'!H32="")))="",FALSE,IF(IFERROR('Harbor Bay monthly P&L and cash'!H26=""=TRUE,FALSE),TRUE,IF(IFERROR('Harbor Bay monthly P&L and cash'!H32=""=TRUE,FALSE),TRUE,OR('Harbor Bay monthly P&L and cash'!H26="",'Harbor Bay monthly P&L and cash'!H32="")))),"",IFERROR(IF(IF(IF(ISERROR('Harbor Bay monthly P&L and cash'!H26<0),'Harbor Bay monthly P&L and cash'!H26<0,IF('Harbor Bay monthly P&L and cash'!H26="","",'Harbor Bay monthly P&L and cash'!H26<0))="",FALSE,IF(ISERROR('Harbor Bay monthly P&L and cash'!H26<0),'Harbor Bay monthly P&L and cash'!H26<0,IF('Harbor Bay monthly P&L and cash'!H26="","",'Harbor Bay monthly P&L and cash'!H26<0))),MAX('Harbor Bay monthly P&L and cash'!H32/(0-'Harbor Bay monthly P&L and cash'!H26),0),""),"")) | I34: =IF(IF(IF(IFERROR('Harbor Bay monthly P&L and cash'!I26=""=TRUE,FALSE),TRUE,IF(IFERROR('Harbor Bay monthly P&L and cash'!I32=""=TRUE,FALSE),TRUE,OR('Harbor Bay monthly P&L and cash'!I26="",'Harbor Bay monthly P&L and cash'!I32="")))="",FALSE,IF(IFERROR('Harbor Bay monthly P&L and cash'!I26=""=TRUE,FALSE),TRUE,IF(IFERROR('Harbor Bay monthly P&L and cash'!I32=""=TRUE,FALSE),TRUE,OR('Harbor Bay monthly P&L and cash'!I26="",'Harbor Bay monthly P&L and cash'!I32="")))),"",IFERROR(IF(IF(IF(ISERROR('Harbor Bay monthly P&L and cash'!I26<0),'Harbor Bay monthly P&L and cash'!I26<0,IF('Harbor Bay monthly P&L and cash'!I26="","",'Harbor Bay monthly P&L and cash'!I26<0))="",FALSE,IF(ISERROR('Harbor Bay monthly P&L and cash'!I26<0),'Harbor Bay monthly P&L and cash'!I26<0,IF('Harbor Bay monthly P&L and cash'!I26="","",'Harbor Bay monthly P&L and cash'!I26<0))),MAX('Harbor Bay monthly P&L and cash'!I32/(0-'Harbor Bay monthly P&L and cash'!I26),0),""),"")) | ... P34: =IF(IF(IF(IFERROR('Harbor Bay monthly P&L and cash'!P26=""=TRUE,FALSE),TRUE,IF(IFERROR('Harbor Bay monthly P&L and cash'!P32=""=TRUE,FALSE),TRUE,OR('Harbor Bay monthly P&L and cash'!P26="",'Harbor Bay monthly P&L and cash'!P32="")))="",FALSE,IF(IFERROR('Harbor Bay monthly P&L and cash'!P26=""=TRUE,FALSE),TRUE,IF(IFERROR('Harbor Bay monthly P&L and cash'!P32=""=TRUE,FALSE),TRUE,OR('Harbor Bay monthly P&L and cash'!P26="",'Harbor Bay monthly P&L and cash'!P32="")))),"",IFERROR(IF(IF(IF(ISERROR('Harbor Bay monthly P&L and cash'!P26<0),'Harbor Bay monthly P&L and cash'!P26<0,IF('Harbor Bay monthly P&L and cash'!P26="","",'Harbor Bay monthly P&L and cash'!P26<0))="",FALSE,IF(ISERROR('Harbor Bay monthly P&L and cash'!P26<0),'Harbor Bay monthly P&L and cash'!P26<0,IF('Harbor Bay monthly P&L and cash'!P26="","",'Harbor Bay monthly P&L and cash'!P26<0))),MAX('Harbor Bay monthly P&L and cash'!P32/(0-'Harbor Bay monthly P&L and cash'!P26),0),""),""))

Sheet Scenario assumptions side by si
A1: Scenario assumptions side by side
A2: Atlas Commerce — Harbor Bay · Base
A4: Variable / dimension | B4: Harbor Bay | C4: Harbor Bay > Growth | D4: Harbor Bay > Downside
A5: Monthly visits | B5: ='Harbor Bay assumptions'!B5 -> 50000 | C5: =65000 -> 65000 | D5: =40000 -> 40000
A6: Conversion rate | B6: ='Harbor Bay assumptions'!B6 -> 0.025 | C6: =0.03 -> 0.03 | D6: =0.018 -> 0.018
A7: Average order value | B7: ='Harbor Bay assumptions'!B7 -> 85 | C7: =90 -> 90 | D7: =78 -> 78
A8: Product cost per order (provisional) | B8: ='Scenario assumptions side by si'!B7*'Catalog product-cost estimation'!B7 -> 42.774903 | C8: ='Scenario assumptions side by si'!C7*'Model inputs'!B22 -> 45.291074 | D8: ='Scenario assumptions side by si'!D7*'Model inputs'!B21 -> 39.252264
A9: Fulfillment cost per order | B9: ='Harbor Bay assumptions'!B9 -> 12 | C9: =11 -> 11 | D9: =14 -> 14
A10: Campaign spend per month | B10: ='Harbor Bay assumptions'!B10 -> 15000 | C10: =20000 -> 20000 | D10: =18000 -> 18000
A11: Inference cost per month | B11: ='Harbor Bay assumptions'!B11 -> 3000 | C11: =3500 -> 3500 | D11: =3500 -> 3500
A12: Infrastructure cost per month (synthetic demo) | B12: ='Harbor Bay assumptions'!B12 -> 500 | C12: ='Harbor Bay assumptions'!B12 -> 500 | D12: =500 -> 500
A13: Opening cash (synthetic demo) | B13: ='Harbor Bay assumptions'!B13 -> 30000 | C13: ='Harbor Bay assumptions'!B13 -> 30000 | D13: =30000 -> 30000

Sheet Scenario outputs — monthly run-
A1: Scenario outputs — monthly run-rate (Oct 2026)
A2: Atlas Commerce — Harbor Bay · Base
A4: Variable / dimension | B4: 2026-10 | C4: 2026-10 > Growth | D4: 2026-10 > Downside
A5: Orders | B5: =SUM('Harbor Bay monthly P&L and cash'!B8) -> 1250 | C5: =SUM('Model inputs'!E64) -> 1950 | D5: =SUM('Model inputs'!E62) -> 720
A6: Revenue | B6: =SUM('Harbor Bay monthly P&L and cash'!B10) -> 106250 | C6: =SUM('Model inputs'!E74) -> 175500 | D6: =SUM('Model inputs'!E72) -> 56160
A7: Gross profit | B7: =SUM('Harbor Bay monthly P&L and cash'!B16) -> 37781.371 | C7: =SUM('Model inputs'!E38) -> 65732.406 | D7: =SUM('Model inputs'!E36) -> 17818.37
A8: Gross margin | B8: =IFERROR('Scenario outputs — monthly run-'!B7/'Scenario outputs — monthly run-'!B6,"") -> 0.35558938 | C8: =IFERROR('Scenario outputs — monthly run-'!C7/'Scenario outputs — monthly run-'!C6,"") -> 0.37454363 | D8: =IFERROR('Scenario outputs — monthly run-'!D7/'Scenario outputs — monthly run-'!D6,"") -> 0.31727867
A9: Contribution before infrastructure (provisional) | B9: ='Scenario outputs — monthly run-'!B7-'Harbor Bay monthly P&L and cash'!B19-'Harbor Bay monthly P&L and cash'!B21 -> 19781.371 | C9: ='Scenario outputs — monthly run-'!C7-'Model inputs'!E13-'Model inputs'!E44 -> 42232.406 | D9: ='Scenario outputs — monthly run-'!D7-'Model inputs'!E12-'Model inputs'!E43 -> -3681.63
A10: Contribution | B10: =IF('Harbor Bay monthly P&L and cash'!B23="","",'Scenario outputs — monthly run-'!B7-'Harbor Bay monthly P&L and cash'!B19-'Harbor Bay monthly P&L and cash'!B21-'Harbor Bay monthly P&L and cash'!B23) -> 19281.371 | C10: =IF('Model inputs'!E50="","",'Scenario outputs — monthly run-'!C7-'Model inputs'!E13-'Model inputs'!E44-'Model inputs'!E50) -> 41732.406 | D10: =IF('Model inputs'!E49="","",'Scenario outputs — monthly run-'!D7-'Model inputs'!E12-'Model inputs'!E43-'Model inputs'!E49) -> -4181.63
A11: Contribution margin | B11: =IF('Scenario outputs — monthly run-'!B10="","",IFERROR('Scenario outputs — monthly run-'!B10/'Scenario outputs — monthly run-'!B6,"")) -> 0.18147173 | C11: =IF('Scenario outputs — monthly run-'!C10="","",IFERROR('Scenario outputs — monthly run-'!C10/'Scenario outputs — monthly run-'!C6,"")) -> 0.23779149 | D11: =IF('Scenario outputs — monthly run-'!D10="","",IFERROR('Scenario outputs — monthly run-'!D10/'Scenario outputs — monthly run-'!D6,"")) -> -0.074459224
A12: Campaign ROI (proxy, not causal) | B12: =IFERROR(('Scenario outputs — monthly run-'!B7-'Harbor Bay monthly P&L and cash'!B19)/'Harbor Bay monthly P&L and cash'!B19,"") -> 1.5187581 | C12: =IFERROR(('Scenario outputs — monthly run-'!C7-'Model inputs'!E13)/'Model inputs'!E13,"") -> 2.2866203 | D12: =IFERROR(('Scenario outputs — monthly run-'!D7-'Model inputs'!E12)/'Model inputs'!E12,"") -> -0.010090556
A13: Cash balance | B13: =IF(IF(IF(IFERROR('Harbor Bay assumptions'!B13=""=TRUE,FALSE),TRUE,IF(IFERROR('Scenario outputs — monthly run-'!B10=""=TRUE,FALSE),TRUE,OR('Harbor Bay assumptions'!B13="",'Scenario outputs — monthly run-'!B10="")))="",FALSE,IF(IFERROR('Harbor Bay assumptions'!B13=""=TRUE,FALSE),TRUE,IF(IFERROR('Scenario outputs — monthly run-'!B10=""=TRUE,FALSE),TRUE,OR('Harbor Bay assumptions'!B13="",'Scenario outputs — monthly run-'!B10="")))),"",'Model inputs'!D16+'Scenario outputs — monthly run-'!B10) -> 49281.371 | C13: =IF(IF(IF(IFERROR('Scenario assumptions side by si'!C13=""=TRUE,FALSE),TRUE,IF(IFERROR('Scenario outputs — monthly run-'!C10=""=TRUE,FALSE),TRUE,OR('Scenario assumptions side by si'!C13="",'Scenario outputs — monthly run-'!C10="")))="",FALSE,IF(IFERROR('Scenario assumptions side by si'!C13=""=TRUE,FALSE),TRUE,IF(IFERROR('Scenario outputs — monthly run-'!C10=""=TRUE,FALSE),TRUE,OR('Scenario assumptions side by si'!C13="",'Scenario outputs — monthly run-'!C10="")))),"",'Model inputs'!D19+'Scenario outputs — monthly run-'!C10) -> 71732.406 | D13: =IF(IF(IF(IFERROR('Scenario assumptions side by si'!D13=""=TRUE,FALSE),TRUE,IF(IFERROR('Scenario outputs — monthly run-'!D10=""=TRUE,FALSE),TRUE,OR('Scenario assumptions side by si'!D13="",'Scenario outputs — monthly run-'!D10="")))="",FALSE,IF(IFERROR('Scenario assumptions side by si'!D13=""=TRUE,FALSE),TRUE,IF(IFERROR('Scenario outputs — monthly run-'!D10=""=TRUE,FALSE),TRUE,OR('Scenario assumptions side by si'!D13="",'Scenario outputs — monthly run-'!D10="")))),"",'Model inputs'!D18+'Scenario outputs — monthly run-'!D10) -> 25818.37
A14: Runway (months, loss cases only) | B14: =IF(IF(IF(IFERROR('Scenario outputs — monthly run-'!B10=""=TRUE,FALSE),TRUE,IF(IFERROR('Scenario outputs — monthly run-'!B13=""=TRUE,FALSE),TRUE,OR('Scenario outputs — monthly run-'!B10="",'Scenario outputs — monthly run-'!B13="")))="",FALSE,IF(IFERROR('Scenario outputs — monthly run-'!B10=""=TRUE,FALSE),TRUE,IF(IFERROR('Scenario outputs — monthly run-'!B13=""=TRUE,FALSE),TRUE,OR('Scenario outputs — monthly run-'!B10="",'Scenario outputs — monthly run-'!B13="")))),"",IFERROR(IF(IF(IF(ISERROR('Scenario outputs — monthly run-'!B10<0),'Scenario outputs — monthly run-'!B10<0,IF('Scenario outputs — monthly run-'!B10="","",'Scenario outputs — monthly run-'!B10<0))="",FALSE,IF(ISERROR('Scenario outputs — monthly run-'!B10<0),'Scenario outputs — monthly run-'!B10<0,IF('Scenario outputs — monthly run-'!B10="","",'Scenario outputs — monthly run-'!B10<0))),MAX('Scenario outputs — monthly run-'!B13/(0-'Scenario outputs — monthly run-'!B10),0),""),"")) | C14: =IF(IF(IF(IFERROR('Scenario outputs — monthly run-'!C10=""=TRUE,FALSE),TRUE,IF(IFERROR('Scenario outputs — monthly run-'!C13=""=TRUE,FALSE),TRUE,OR('Scenario outputs — monthly run-'!C10="",'Scenario outputs — monthly run-'!C13="")))="",FALSE,IF(IFERROR('Scenario outputs — monthly run-'!C10=""=TRUE,FALSE),TRUE,IF(IFERROR('Scenario outputs — monthly run-'!C13=""=TRUE,FALSE),TRUE,OR('Scenario outputs — monthly run-'!C10="",'Scenario outputs — monthly run-'!C13="")))),"",IFERROR(IF(IF(IF(ISERROR('Scenario outputs — monthly run-'!C10<0),'Scenario outputs — monthly run-'!C10<0,IF('Scenario outputs — monthly run-'!C10="","",'Scenario outputs — monthly run-'!C10<0))="",FALSE,IF(ISERROR('Scenario outputs — monthly run-'!C10<0),'Scenario outputs — monthly run-'!C10<0,IF('Scenario outputs — monthly run-'!C10="","",'Scenario outputs — monthly run-'!C10<0))),MAX('Scenario outputs — monthly run-'!C13/(0-'Scenario outputs — monthly run-'!C10),0),""),"")) | D14: =IF(IF(IF(IFERROR('Scenario outputs — monthly run-'!D10=""=TRUE,FALSE),TRUE,IF(IFERROR('Scenario outputs — monthly run-'!D13=""=TRUE,FALSE),TRUE,OR('Scenario outputs — monthly run-'!D10="",'Scenario outputs — monthly run-'!D13="")))="",FALSE,IF(IFERROR('Scenario outputs — monthly run-'!D10=""=TRUE,FALSE),TRUE,IF(IFERROR('Scenario outputs — monthly run-'!D13=""=TRUE,FALSE),TRUE,OR('Scenario outputs — monthly run-'!D10="",'Scenario outputs — monthly run-'!D13="")))),"",IFERROR(IF(IF(IF(ISERROR('Scenario outputs — monthly run-'!D10<0),'Scenario outputs — monthly run-'!D10<0,IF('Scenario outputs — monthly run-'!D10="","",'Scenario outputs — monthly run-'!D10<0))="",FALSE,IF(ISERROR('Scenario outputs — monthly run-'!D10<0),'Scenario outputs — monthly run-'!D10<0,IF('Scenario outputs — monthly run-'!D10="","",'Scenario outputs — monthly run-'!D10<0))),MAX('Scenario outputs — monthly run-'!D13/(0-'Scenario outputs — monthly run-'!D10),0),""),"")) -> 6.1742359

Sheet Seed product catalog — provisio
A1: Seed product catalog — provisional equal-unit mix
A2: Atlas Commerce — Harbor Bay · Base
A4: Variable / dimension | B4: Catalog product name | C4: Catalog price | D4: Catalog cost | E4: Seed base popularity | F4: Assumed unit mix weight (provisional) | G4: Weighted catalog price | H4: Weighted catalog cost
A5: boots | B5: ="Trail Boots" -> Trail Boots | C5: =120 -> 120 | D5: =65 -> 65 | E5: =3 -> 3 | F5: =1 -> 1 | G5: ='Seed product catalog — provisio'!C5*'Seed product catalog — provisio'!F5 -> 120 | H5: ='Seed product catalog — provisio'!D5*'Seed product catalog — provisio'!F5 -> 65
A6: bottle | B6: ="Insulated Bottle" -> Insulated Bottle | C6: =35 -> 35 | D6: =15 -> 15 | E6: =3 -> 3 | F6: =1 -> 1 | G6: ='Seed product catalog — provisio'!C6*'Seed product catalog — provisio'!F6 -> 35 | H6: ='Seed product catalog — provisio'!D6*'Seed product catalog — provisio'!F6 -> 15
A7: charger | B7: ="Portable Charger 20000mAh" -> Portable Charger 20000mAh | C7: =45 -> 45 | D7: =22 -> 22 | E7: =2 -> 2 | F7: =1 -> 1 | G7: ='Seed product catalog — provisio'!C7*'Seed product catalog — provisio'!F7 -> 45 | H7: ='Seed product catalog — provisio'!D7*'Seed product catalog — provisio'!F7 -> 22
A8: lights | B8: ="LED String Lights" -> LED String Lights | C8: =18 -> 18 | D8: =7 -> 7 | E8: =1 -> 1 | F8: =1 -> 1 | G8: ='Seed product catalog — provisio'!C8*'Seed product catalog — provisio'!F8 -> 18 | H8: ='Seed product catalog — provisio'!D8*'Seed product catalog — provisio'!F8 -> 7
A9: pack | B9: ="Hiking Pack 45L" -> Hiking Pack 45L | C9: =160 -> 160 | D9: =85 -> 85 | E9: =2 -> 2 | F9: =1 -> 1 | G9: ='Seed product catalog — provisio'!C9*'Seed product catalog — provisio'!F9 -> 160 | H9: ='Seed product catalog — provisio'!D9*'Seed product catalog — provisio'!F9 -> 85
A10: poles | B10: ="Trekking Poles" -> Trekking Poles | C10: =90 -> 90 | D10: =45 -> 45 | E10: =1 -> 1 | F10: =1 -> 1 | G10: ='Seed product catalog — provisio'!C10*'Seed product catalog — provisio'!F10 -> 90 | H10: ='Seed product catalog — provisio'!D10*'Seed product catalog — provisio'!F10 -> 45
A11: pouch | B11: ="Festival Phone Pouch" -> Festival Phone Pouch | C11: =25 -> 25 | D11: =10 -> 10 | E11: =1 -> 1 | F11: =1 -> 1 | G11: ='Seed product catalog — provisio'!C11*'Seed product catalog — provisio'!F11 -> 25 | H11: ='Seed product catalog — provisio'!D11*'Seed product catalog — provisio'!F11 -> 10
A12: tent | B12: ="Backpacking Tent" -> Backpacking Tent | C12: =280 -> 280 | D12: =140 -> 140 | E12: =2 -> 2 | F12: =1 -> 1 | G12: ='Seed product catalog — provisio'!C12*'Seed product catalog — provisio'!F12 -> 280 | H12: ='Seed product catalog — provisio'!D12*'Seed product catalog — provisio'!F12 -> 140

Sheet Catalog product-cost estimation
A1: Catalog product-cost estimation method
A2: Atlas Commerce — Harbor Bay · Base
A4: Variable / dimension | B4: Value
A5: Assumed basket price total | B5: =SUM('Seed product catalog — provisio'!G5,'Seed product catalog — provisio'!G6,'Seed product catalog — provisio'!G7,'Seed product catalog — provisio'!G8,'Seed product catalog — provisio'!G9,'Seed product catalog — provisio'!G10,'Seed product catalog — provisio'!G11,'Seed product catalog — provisio'!G12) -> 773
A6: Assumed basket cost total | B6: =SUM('Seed product catalog — provisio'!H5,'Seed product catalog — provisio'!H6,'Seed product catalog — provisio'!H7,'Seed product catalog — provisio'!H8,'Seed product catalog — provisio'!H9,'Seed product catalog — provisio'!H10,'Seed product catalog — provisio'!H11,'Seed product catalog — provisio'!H12) -> 389
A7: Catalog cost-to-sales ratio (provisional) | B7: =IFERROR('Catalog product-cost estimation'!B6/'Catalog product-cost estimation'!B5,"") -> 0.50323415

Sheet Known-cost contribution and cov
A1: Known-cost contribution and coverage
A2: Atlas Commerce — Harbor Bay · Base
A4: Variable / dimension | B4: 2026-10 | C4: 2026-11 | D4: 2026-12 | E4: 2027-01 | F4: 2027-02 | G4: 2027-03 | H4: 2027-04 | I4: 2027-05 | J4: 2027-06 | K4: 2027-07 | L4: 2027-08 | M4: 2027-09 | N4: 2027-10 | O4: 2027-11 | P4: 2027-12
A5: Contribution before infrastructure (provisional) | B5: ='Harbor Bay monthly P&L and cash'!B15-'Harbor Bay monthly P&L and cash'!B19-'Harbor Bay monthly P&L and cash'!B21 -> 19781.371 | C5: ='Harbor Bay monthly P&L and cash'!C15-'Harbor Bay monthly P&L and cash'!C19-'Harbor Bay monthly P&L and cash'!C21 -> 19781.371 | D5: ='Harbor Bay monthly P&L and cash'!D15-'Harbor Bay monthly P&L and cash'!D19-'Harbor Bay monthly P&L and cash'!D21 -> 19781.371 | E5: ='Harbor Bay monthly P&L and cash'!E15-'Harbor Bay monthly P&L and cash'!E19-'Harbor Bay monthly P&L and cash'!E21 -> 19781.371 | F5: ='Harbor Bay monthly P&L and cash'!F15-'Harbor Bay monthly P&L and cash'!F19-'Harbor Bay monthly P&L and cash'!F21 -> 19781.371 | G5: ='Harbor Bay monthly P&L and cash'!G15-'Harbor Bay monthly P&L and cash'!G19-'Harbor Bay monthly P&L and cash'!G21 -> 19781.371 | H5: ='Harbor Bay monthly P&L and cash'!H15-'Harbor Bay monthly P&L and cash'!H19-'Harbor Bay monthly P&L and cash'!H21 -> 19781.371 | I5: ='Harbor Bay monthly P&L and cash'!I15-'Harbor Bay monthly P&L and cash'!I19-'Harbor Bay monthly P&L and cash'!I21 -> 19781.371 | ... P5: ='Harbor Bay monthly P&L and cash'!P15-'Harbor Bay monthly P&L and cash'!P19-'Harbor Bay monthly P&L and cash'!P21 -> 19781.371
A6: Harbor Bay | B6: ='Harbor Bay monthly P&L and cash'!B16-'Harbor Bay monthly P&L and cash'!B20-'Harbor Bay monthly P&L and cash'!B22 -> 19781.371 | C6: ='Harbor Bay monthly P&L and cash'!C16-'Harbor Bay monthly P&L and cash'!C20-'Harbor Bay monthly P&L and cash'!C22 -> 19781.371 | D6: ='Harbor Bay monthly P&L and cash'!D16-'Harbor Bay monthly P&L and cash'!D20-'Harbor Bay monthly P&L and cash'!D22 -> 19781.371 | E6: ='Harbor Bay monthly P&L and cash'!E16-'Harbor Bay monthly P&L and cash'!E20-'Harbor Bay monthly P&L and cash'!E22 -> 19781.371 | F6: ='Harbor Bay monthly P&L and cash'!F16-'Harbor Bay monthly P&L and cash'!F20-'Harbor Bay monthly P&L and cash'!F22 -> 19781.371 | G6: ='Harbor Bay monthly P&L and cash'!G16-'Harbor Bay monthly P&L and cash'!G20-'Harbor Bay monthly P&L and cash'!G22 -> 19781.371 | H6: ='Harbor Bay monthly P&L and cash'!H16-'Harbor Bay monthly P&L and cash'!H20-'Harbor Bay monthly P&L and cash'!H22 -> 19781.371 | I6: ='Harbor Bay monthly P&L and cash'!I16-'Harbor Bay monthly P&L and cash'!I20-'Harbor Bay monthly P&L and cash'!I22 -> 19781.371 | ... P6: ='Harbor Bay monthly P&L and cash'!P16-'Harbor Bay monthly P&L and cash'!P20-'Harbor Bay monthly P&L and cash'!P22 -> 19781.371
A7: Seed projected profit (inconsistent, not an output) | B7: ="UNRESOLVED: $125,000 seed projection exceeds $106,250 base revenue" -> UNRESOLVED: $125,000 seed projection exceeds $106,250 base revenue | C7: ="UNRESOLVED: $125,000 seed projection exceeds $106,250 base revenue" -> UNRESOLVED: $125,000 seed projection exceeds $106,250 base revenue | D7: ="UNRESOLVED: $125,000 seed projection exceeds $106,250 base revenue" -> UNRESOLVED: $125,000 seed projection exceeds $106,250 base revenue | E7: ="UNRESOLVED: $125,000 seed projection exceeds $106,250 base revenue" -> UNRESOLVED: $125,000 seed projection exceeds $106,250 base revenue | F7: ="UNRESOLVED: $125,000 seed projection exceeds $106,250 base revenue" -> UNRESOLVED: $125,000 seed projection exceeds $106,250 base revenue | G7: ="UNRESOLVED: $125,000 seed projection exceeds $106,250 base revenue" -> UNRESOLVED: $125,000 seed projection exceeds $106,250 base revenue | H7: ="UNRESOLVED: $125,000 seed projection exceeds $106,250 base revenue" -> UNRESOLVED: $125,000 seed projection exceeds $106,250 base revenue | I7: ="UNRESOLVED: $125,000 seed projection exceeds $106,250 base revenue" -> UNRESOLVED: $125,000 seed projection exceeds $106,250 base revenue | ... P7: ="UNRESOLVED: $125,000 seed projection exceeds $106,250 base revenue" -> UNRESOLVED: $125,000 seed projection exceeds $106,250 base revenue

Sheet Model inputs
A1: Model inputs
A2: Integration values are aggregated snapshots; raw source records are not included.
A4: Variables
A5: Variable / segment | B5: Value | C5: Value | D5: 2026-09 | E5: 2026-10 | F5: 2026-11 | G5: 2026-12 | H5: 2027-01 | I5: 2027-02 | J5: 2027-03 | K5: 2027-04 | L5: 2027-05 | M5: 2027-06 | N5: 2027-07 | O5: 2027-08 | P5: 2027-09 | Q5: 2027-10 | R5: 2027-11 | S5: 2027-12
A6: Average order value | B6: =SUM('Model inputs'!B7) -> 85
A7: Average order value > Harbor Bay | B7: ='Harbor Bay assumptions'!B7 -> 85
A8: Average order value | C8: =SUM('Model inputs'!B7) -> 85
A9: Average order value > Harbor Bay | C9: ='Harbor Bay assumptions'!B7 -> 85
A10: Campaign expense | D10: =SUM('Model inputs'!D11) -> 0 | E10: =SUM('Model inputs'!E11) -> 15000 | F10: =SUM('Model inputs'!F11) -> 15000 | G10: =SUM('Model inputs'!G11) -> 15000 | H10: =SUM('Model inputs'!H11) -> 15000 | I10: =SUM('Model inputs'!I11) -> 15000 | J10: =SUM('Model inputs'!J11) -> 15000 | K10: =SUM('Model inputs'!K11) -> 15000 | ... S10: =SUM('Model inputs'!S11) -> 15000
A11: Campaign expense > Harbor Bay | D11: =0 -> 0 | E11: =IF('Model inputs'!C15="","",'Model inputs'!C15) -> 15000 | F11: =IF('Model inputs'!C15="","",'Model inputs'!C15) -> 15000 | G11: =IF('Model inputs'!C15="","",'Model inputs'!C15) -> 15000 | H11: =IF('Model inputs'!C15="","",'Model inputs'!C15) -> 15000 | I11: =IF('Model inputs'!C15="","",'Model inputs'!C15) -> 15000 | J11: =IF('Model inputs'!C15="","",'Model inputs'!C15) -> 15000 | K11: =IF('Model inputs'!C15="","",'Model inputs'!C15) -> 15000 | L11: =IF('Model inputs'!C15="","",'Model inputs'!C15) -> 15000 | M11: =IF('Model inputs'!C15="","",'Model inputs'!C15) -> 15000 | N11: =IF('Model inputs'!C15="","",'Model inputs'!C15) -> 15000 | O11: =IF('Model inputs'!C15="","",'Model inputs'!C15) -> 15000 | P11: =IF('Model inputs'!C15="","",'Model inputs'!C15) -> 15000 | Q11: =IF('Model inputs'!C15="","",'Model inputs'!C15) -> 15000 | R11: =IF('Model inputs'!C15="","",'Model inputs'!C15) -> 15000 | S11: =IF('Model inputs'!C15="","",'Model inputs'!C15) -> 15000
A12: Campaign expense · Downside | D12: =SUM('Model inputs'!D129) -> 0 | E12: =SUM('Model inputs'!E129) -> 18000
A13: Campaign expense · Growth | D13: =SUM('Model inputs'!D131) -> 0 | E13: =SUM('Model inputs'!E131) -> 20000
A14: Campaign spend per month | C14: =SUM('Model inputs'!C15) -> 15000
A15: Campaign spend per month > Harbor Bay | C15: ='Harbor Bay assumptions'!B10 -> 15000
A16: Cash balance | D16: =IF('Model inputs'!C54="","",'Model inputs'!C54) -> 30000 | E16: =IF(IF(IF(IFERROR('Model inputs'!C54=""=TRUE,FALSE),TRUE,IF(IFERROR('Model inputs'!E23=""=TRUE,FALSE),TRUE,OR('Model inputs'!C54="",'Model inputs'!E23="")))="",FALSE,IF(IFERROR('Model inputs'!C54=""=TRUE,FALSE),TRUE,IF(IFERROR('Model inputs'!E23=""=TRUE,FALSE),TRUE,OR('Model inputs'!C54="",'Model inputs'!E23="")))),"",'Model inputs'!D16+'Model inputs'!E23) -> 49281.371 | F16: =IF(IF(IF(IFERROR('Model inputs'!C54=""=TRUE,FALSE),TRUE,IF(IFERROR('Model inputs'!F23=""=TRUE,FALSE),TRUE,OR('Model inputs'!C54="",'Model inputs'!F23="")))="",FALSE,IF(IFERROR('Model inputs'!C54=""=TRUE,FALSE),TRUE,IF(IFERROR('Model inputs'!F23=""=TRUE,FALSE),TRUE,OR('Model inputs'!C54="",'Model inputs'!F23="")))),"",'Model inputs'!E16+'Model inputs'!F23) -> 68562.743 | G16: =IF(IF(IF(IFERROR('Model inputs'!C54=""=TRUE,FALSE),TRUE,IF(IFERROR('Model inputs'!G23=""=TRUE,FALSE),TRUE,OR('Model inputs'!C54="",'Model inputs'!G23="")))="",FALSE,IF(IFERROR('Model inputs'!C54=""=TRUE,FALSE),TRUE,IF(IFERROR('Model inputs'!G23=""=TRUE,FALSE),TRUE,OR('Model inputs'!C54="",'Model inputs'!G23="")))),"",'Model inputs'!F16+'Model inputs'!G23) -> 87844.114 | H16: =IF(IF(IF(IFERROR('Model inputs'!C54=""=TRUE,FALSE),TRUE,IF(IFERROR('Model inputs'!H23=""=TRUE,FALSE),TRUE,OR('Model inputs'!C54="",'Model inputs'!H23="")))="",FALSE,IF(IFERROR('Model inputs'!C54=""=TRUE,FALSE),TRUE,IF(IFERROR('Model inputs'!H23=""=TRUE,FALSE),TRUE,OR('Model inputs'!C54="",'Model inputs'!H23="")))),"",'Model inputs'!G16+'Model inputs'!H23) -> 107125.49 | I16: =IF(IF(IF(IFERROR('Model inputs'!C54=""=TRUE,FALSE),TRUE,IF(IFERROR('Model inputs'!I23=""=TRUE,FALSE),TRUE,OR('Model inputs'!C54="",'Model inputs'!I23="")))="",FALSE,IF(IFERROR('Model inputs'!C54=""=TRUE,FALSE),TRUE,IF(IFERROR('Model inputs'!I23=""=TRUE,FALSE),TRUE,OR('Model inputs'!C54="",'Model inputs'!I23="")))),"",'Model inputs'!H16+'Model inputs'!I23) -> 126406.86 | J16: =IF(IF(IF(IFERROR('Model inputs'!C54=""=TRUE,FALSE),TRUE,IF(IFERROR('Model inputs'!J23=""=TRUE,FALSE),TRUE,OR('Model inputs'!C54="",'Model inputs'!J23="")))="",FALSE,IF(IFERROR('Model inputs'!C54=""=TRUE,FALSE),TRUE,IF(IFERROR('Model inputs'!J23=""=TRUE,FALSE),TRUE,OR('Model inputs'!C54="",'Model inputs'!J23="")))),"",'Model inputs'!I16+'Model inputs'!J23) -> 145688.23 | K16: =IF(IF(IF(IFERROR('Model inputs'!C54=""=TRUE,FALSE),TRUE,IF(IFERROR('Model inputs'!K23=""=TRUE,FALSE),TRUE,OR('Model inputs'!C54="",'Model inputs'!K23="")))="",FALSE,IF(IFERROR('Model inputs'!C54=""=TRUE,FALSE),TRUE,IF(IFERROR('Model inputs'!K23=""=TRUE,FALSE),TRUE,OR('Model inputs'!C54="",'Model inputs'!K23="")))),"",'Model inputs'!J16+'Model inputs'!K23) -> 164969.6 | L16: =IF(IF(IF(IFERROR('Model inputs'!C54=""=TRUE,FALSE),TRUE,IF(IFERROR('Model inputs'!L23=""=TRUE,FALSE),TRUE,OR('Model inputs'!C54="",'Model inputs'!L23="")))="",FALSE,IF(IFERROR('Model inputs'!C54=""=TRUE,FALSE),TRUE,IF(IFERROR('Model inputs'!L23=""=TRUE,FALSE),TRUE,OR('Model inputs'!C54="",'Model inputs'!L23="")))),"",'Model inputs'!K16+'Model inputs'!L23) -> 184250.97 | M16: =IF(IF(IF(IFERROR('Model inputs'!C54=""=TRUE,FALSE),TRUE,IF(IFERROR('Model inputs'!M23=""=TRUE,FALSE),TRUE,OR('Model inputs'!C54="",'Model inputs'!M23="")))="",FALSE,IF(IFERROR('Model inputs'!C54=""=TRUE,FALSE),TRUE,IF(IFERROR('Model inputs'!M23=""=TRUE,FALSE),TRUE,OR('Model inputs'!C54="",'Model inputs'!M23="")))),"",'Model inputs'!L16+'Model inputs'!M23) -> 203532.34 | N16: =IF(IF(IF(IFERROR('Model inputs'!C54=""=TRUE,FALSE),TRUE,IF(IFERROR('Model inputs'!N23=""=TRUE,FALSE),TRUE,OR('Model inputs'!C54="",'Model inputs'!N23="")))="",FALSE,IF(IFERROR('Model inputs'!C54=""=TRUE,FALSE),TRUE,IF(IFERROR('Model inputs'!N23=""=TRUE,FALSE),TRUE,OR('Model inputs'!C54="",'Model inputs'!N23="")))),"",'Model inputs'!M16+'Model inputs'!N23) -> 222813.71 | O16: =IF(IF(IF(IFERROR('Model inputs'!C54=""=TRUE,FALSE),TRUE,IF(IFERROR('Model inputs'!O23=""=TRUE,FALSE),TRUE,OR('Model inputs'!C54="",'Model inputs'!O23="")))="",FALSE,IF(IFERROR('Model inputs'!C54=""=TRUE,FALSE),TRUE,IF(IFERROR('Model inputs'!O23=""=TRUE,FALSE),TRUE,OR('Model inputs'!C54="",'Model inputs'!O23="")))),"",'Model inputs'!N16+'Model inputs'!O23) -> 242095.08 | P16: =IF(IF(IF(IFERROR('Model inputs'!C54=""=TRUE,FALSE),TRUE,IF(IFERROR('Model inputs'!P23=""=TRUE,FALSE),TRUE,OR('Model inputs'!C54="",'Model inputs'!P23="")))="",FALSE,IF(IFERROR('Model inputs'!C54=""=TRUE,FALSE),TRUE,IF(IFERROR('Model inputs'!P23=""=TRUE,FALSE),TRUE,OR('Model inputs'!C54="",'Model inputs'!P23="")))),"",'Model inputs'!O16+'Model inputs'!P23) -> 261376.46 | Q16: =IF(IF(IF(IFERROR('Model inputs'!C54=""=TRUE,FALSE),TRUE,IF(IFERROR('Model inputs'!Q23=""=TRUE,FALSE),TRUE,OR('Model inputs'!C54="",'Model inputs'!Q23="")))="",FALSE,IF(IFERROR('Model inputs'!C54=""=TRUE,FALSE),TRUE,IF(IFERROR('Model inputs'!Q23=""=TRUE,FALSE),TRUE,OR('Model inputs'!C54="",'Model inputs'!Q23="")))),"",'Model inputs'!P16+'Model inputs'!Q23) -> 280657.83 | R16: =IF(IF(IF(IFERROR('Model inputs'!C54=""=TRUE,FALSE),TRUE,IF(IFERROR('Model inputs'!R23=""=TRUE,FALSE),TRUE,OR('Model inputs'!C54="",'Model inputs'!R23="")))="",FALSE,IF(IFERROR('Model inputs'!C54=""=TRUE,FALSE),TRUE,IF(IFERROR('Model inputs'!R23=""=TRUE,FALSE),TRUE,OR('Model inputs'!C54="",'Model inputs'!R23="")))),"",'Model inputs'!Q16+'Model inputs'!R23) -> 299939.2 | S16: =IF(IF(IF(IFERROR('Model inputs'!C54=""=TRUE,FALSE),TRUE,IF(IFERROR('Model inputs'!S23=""=TRUE,FALSE),TRUE,OR('Model inputs'!C54="",'Model inputs'!S23="")))="",FALSE,IF(IFERROR('Model inputs'!C54=""=TRUE,FALSE),TRUE,IF(IFERROR('Model inputs'!S23=""=TRUE,FALSE),TRUE,OR('Model inputs'!C54="",'Model inputs'!S23="")))),"",'Model inputs'!R16+'Model inputs'!S23) -> 319220.57
A17: Cash balance > Harbor Bay | D17: =IF('Model inputs'!C54="","",'Model inputs'!C54) -> 30000 | E17: =IF(IF(IF(IFERROR('Model inputs'!C54=""=TRUE,FALSE),TRUE,IF(IFERROR('Model inputs'!E24=""=TRUE,FALSE),TRUE,OR('Model inputs'!C54="",'Model inputs'!E24="")))="",FALSE,IF(IFERROR('Model inputs'!C54=""=TRUE,FALSE),TRUE,IF(IFERROR('Model inputs'!E24=""=TRUE,FALSE),TRUE,OR('Model inputs'!C54="",'Model inputs'!E24="")))),"",'Model inputs'!D17+'Model inputs'!E24) -> 49281.371 | F17: =IF(IF(IF(IFERROR('Model inputs'!C54=""=TRUE,FALSE),TRUE,IF(IFERROR('Model inputs'!F24=""=TRUE,FALSE),TRUE,OR('Model inputs'!C54="",'Model inputs'!F24="")))="",FALSE,IF(IFERROR('Model inputs'!C54=""=TRUE,FALSE),TRUE,IF(IFERROR('Model inputs'!F24=""=TRUE,FALSE),TRUE,OR('Model inputs'!C54="",'Model inputs'!F24="")))),"",'Model inputs'!E17+'Model inputs'!F24) -> 68562.743 | G17: =IF(IF(IF(IFERROR('Model inputs'!C54=""=TRUE,FALSE),TRUE,IF(IFERROR('Model inputs'!G24=""=TRUE,FALSE),TRUE,OR('Model inputs'!C54="",'Model inputs'!G24="")))="",FALSE,IF(IFERROR('Model inputs'!C54=""=TRUE,FALSE),TRUE,IF(IFERROR('Model inputs'!G24=""=TRUE,FALSE),TRUE,OR('Model inputs'!C54="",'Model inputs'!G24="")))),"",'Model inputs'!F17+'Model inputs'!G24) -> 87844.114 | H17: =IF(IF(IF(IFERROR('Model inputs'!C54=""=TRUE,FALSE),TRUE,IF(IFERROR('Model inputs'!H24=""=TRUE,FALSE),TRUE,OR('Model inputs'!C54="",'Model inputs'!H24="")))="",FALSE,IF(IFERROR('Model inputs'!C54=""=TRUE,FALSE),TRUE,IF(IFERROR('Model inputs'!H24=""=TRUE,FALSE),TRUE,OR('Model inputs'!C54="",'Model inputs'!H24="")))),"",'Model inputs'!G17+'Model inputs'!H24) -> 107125.49 | I17: =IF(IF(IF(IFERROR('Model inputs'!C54=""=TRUE,FALSE),TRUE,IF(IFERROR('Model inputs'!I24=""=TRUE,FALSE),TRUE,OR('Model inputs'!C54="",'Model inputs'!I24="")))="",FALSE,IF(IFERROR('Model inputs'!C54=""=TRUE,FALSE),TRUE,IF(IFERROR('Model inputs'!I24=""=TRUE,FALSE),TRUE,OR('Model inputs'!C54="",'Model inputs'!I24="")))),"",'Model inputs'!H17+'Model inputs'!I24) -> 126406.86 | J17: =IF(IF(IF(IFERROR('Model inputs'!C54=""=TRUE,FALSE),TRUE,IF(IFERROR('Model inputs'!J24=""=TRUE,FALSE),TRUE,OR('Model inputs'!C54="",'Model inputs'!J24="")))="",FALSE,IF(IFERROR('Model inputs'!C54=""=TRUE,FALSE),TRUE,IF(IFERROR('Model inputs'!J24=""=TRUE,FALSE),TRUE,OR('Model inputs'!C54="",'Model inputs'!J24="")))),"",'Model inputs'!I17+'Model inputs'!J24) -> 145688.23 | K17: =IF(IF(IF(IFERROR('Model inputs'!C54=""=TRUE,FALSE),TRUE,IF(IFERROR('Model inputs'!K24=""=TRUE,FALSE),TRUE,OR('Model inputs'!C54="",'Model inputs'!K24="")))="",FALSE,IF(IFERROR('Model inputs'!C54=""=TRUE,FALSE),TRUE,IF(IFERROR('Model inputs'!K24=""=TRUE,FALSE),TRUE,OR('Model inputs'!C54="",'Model inputs'!K24="")))),"",'Model inputs'!J17+'Model inputs'!K24) -> 164969.6 | L17: =IF(IF(IF(IFERROR('Model inputs'!C54=""=TRUE,FALSE),TRUE,IF(IFERROR('Model inputs'!L24=""=TRUE,FALSE),TRUE,OR('Model inputs'!C54="",'Model inputs'!L24="")))="",FALSE,IF(IFERROR('Model inputs'!C54=""=TRUE,FALSE),TRUE,IF(IFERROR('Model inputs'!L24=""=TRUE,FALSE),TRUE,OR('Model inputs'!C54="",'Model inputs'!L24="")))),"",'Model inputs'!K17+'Model inputs'!L24) -> 184250.97 | M17: =IF(IF(IF(IFERROR('Model inputs'!C54=""=TRUE,FALSE),TRUE,IF(IFERROR('Model inputs'!M24=""=TRUE,FALSE),TRUE,OR('Model inputs'!C54="",'Model inputs'!M24="")))="",FALSE,IF(IFERROR('Model inputs'!C54=""=TRUE,FALSE),TRUE,IF(IFERROR('Model inputs'!M24=""=TRUE,FALSE),TRUE,OR('Model inputs'!C54="",'Model inputs'!M24="")))),"",'Model inputs'!L17+'Model inputs'!M24) -> 203532.34 | N17: =IF(IF(IF(IFERROR('Model inputs'!C54=""=TRUE,FALSE),TRUE,IF(IFERROR('Model inputs'!N24=""=TRUE,FALSE),TRUE,OR('Model inputs'!C54="",'Model inputs'!N24="")))="",FALSE,IF(IFERROR('Model inputs'!C54=""=TRUE,FALSE),TRUE,IF(IFERROR('Model inputs'!N24=""=TRUE,FALSE),TRUE,OR('Model inputs'!C54="",'Model inputs'!N24="")))),"",'Model inputs'!M17+'Model inputs'!N24) -> 222813.71 | O17: =IF(IF(IF(IFERROR('Model inputs'!C54=""=TRUE,FALSE),TRUE,IF(IFERROR('Model inputs'!O24=""=TRUE,FALSE),TRUE,OR('Model inputs'!C54="",'Model inputs'!O24="")))="",FALSE,IF(IFERROR('Model inputs'!C54=""=TRUE,FALSE),TRUE,IF(IFERROR('Model inputs'!O24=""=TRUE,FALSE),TRUE,OR('Model inputs'!C54="",'Model inputs'!O24="")))),"",'Model inputs'!N17+'Model inputs'!O24) -> 242095.08 | P17: =IF(IF(IF(IFERROR('Model inputs'!C54=""=TRUE,FALSE),TRUE,IF(IFERROR('Model inputs'!P24=""=TRUE,FALSE),TRUE,OR('Model inputs'!C54="",'Model inputs'!P24="")))="",FALSE,IF(IFERROR('Model inputs'!C54=""=TRUE,FALSE),TRUE,IF(IFERROR('Model inputs'!P24=""=TRUE,FALSE),TRUE,OR('Model inputs'!C54="",'Model inputs'!P24="")))),"",'Model inputs'!O17+'Model inputs'!P24) -> 261376.46 | Q17: =IF(IF(IF(IFERROR('Model inputs'!C54=""=TRUE,FALSE),TRUE,IF(IFERROR('Model inputs'!Q24=""=TRUE,FALSE),TRUE,OR('Model inputs'!C54="",'Model inputs'!Q24="")))="",FALSE,IF(IFERROR('Model inputs'!C54=""=TRUE,FALSE),TRUE,IF(IFERROR('Model inputs'!Q24=""=TRUE,FALSE),TRUE,OR('Model inputs'!C54="",'Model inputs'!Q24="")))),"",'Model inputs'!P17+'Model inputs'!Q24) -> 280657.83 | R17: =IF(IF(IF(IFERROR('Model inputs'!C54=""=TRUE,FALSE),TRUE,IF(IFERROR('Model inputs'!R24=""=TRUE,FALSE),TRUE,OR('Model inputs'!C54="",'Model inputs'!R24="")))="",FALSE,IF(IFERROR('Model inputs'!C54=""=TRUE,FALSE),TRUE,IF(IFERROR('Model inputs'!R24=""=TRUE,FALSE),TRUE,OR('Model inputs'!C54="",'Model inputs'!R24="")))),"",'Model inputs'!Q17+'Model inputs'!R24) -> 299939.2 | S17: =IF(IF(IF(IFERROR('Model inputs'!C54=""=TRUE,FALSE),TRUE,IF(IFERROR('Model inputs'!S24=""=TRUE,FALSE),TRUE,OR('Model inputs'!C54="",'Model inputs'!S24="")))="",FALSE,IF(IFERROR('Model inputs'!C54=""=TRUE,FALSE),TRUE,IF(IFERROR('Model inputs'!S24=""=TRUE,FALSE),TRUE,OR('Model inputs'!C54="",'Model inputs'!S24="")))),"",'Model inputs'!R17+'Model inputs'!S24) -> 319220.57
A18: Cash balance · Downside | D18: =IF('Model inputs'!C56="","",'Model inputs'!C56) -> 30000 | E18: =IF(IF(IF(IFERROR('Model inputs'!C56=""=TRUE,FALSE),TRUE,IF(IFERROR('Model inputs'!E25=""=TRUE,FALSE),TRUE,OR('Model inputs'!C56="",'Model inputs'!E25="")))="",FALSE,IF(IFERROR('Model inputs'!C56=""=TRUE,FALSE),TRUE,IF(IFERROR('Model inputs'!E25=""=TRUE,FALSE),TRUE,OR('Model inputs'!C56="",'Model inputs'!E25="")))),"",'Model inputs'!D18+'Model inputs'!E25) -> 25818.37
A19: Cash balance · Growth | D19: =IF('Model inputs'!C58="","",'Model inputs'!C58) -> 30000 | E19: =IF(IF(IF(IFERROR('Model inputs'!C58=""=TRUE,FALSE),TRUE,IF(IFERROR('Model inputs'!E26=""=TRUE,FALSE),TRUE,OR('Model inputs'!C58="",'Model inputs'!E26="")))="",FALSE,IF(IFERROR('Model inputs'!C58=""=TRUE,FALSE),TRUE,IF(IFERROR('Model inputs'!E26=""=TRUE,FALSE),TRUE,OR('Model inputs'!C58="",'Model inputs'!E26="")))),"",'Model inputs'!D19+'Model inputs'!E26) -> 71732.406
A20: Catalog cost-to-sales ratio (provisional) · Harbor Bay assumptions · Base | B20: =IFERROR('Model inputs'!B77/'Model inputs'!B78,"") -> 0.50323415
A21: Catalog cost-to-sales ratio (provisional) · Downside | B21: =IFERROR('Model inputs'!B124/'Model inputs'!B126,"") -> 0.50323415
A22: Catalog cost-to-sales ratio (provisional) · Growth | B22: =IFERROR('Model inputs'!B125/'Model inputs'!B127,"") -> 0.50323415
A23: Contribution | D23: =SUM('Model inputs'!D24) -> 0 | E23: =IF('Model inputs'!E47="","",'Model inputs'!E33-'Model inputs'!E10-'Model inputs'!E41-'Model inputs'!E47) -> 19281.371 | F23: =IF('Model inputs'!F47="","",'Model inputs'!F33-'Model inputs'!F10-'Model inputs'!F41-'Model inputs'!F47) -> 19281.371 | G23: =IF('Model inputs'!G47="","",'Model inputs'!G33-'Model inputs'!G10-'Model inputs'!G41-'Model inputs'!G47) -> 19281.371 | H23: =IF('Model inputs'!H47="","",'Model inputs'!H33-'Model inputs'!H10-'Model inputs'!H41-'Model inputs'!H47) -> 19281.371 | I23: =IF('Model inputs'!I47="","",'Model inputs'!I33-'Model inputs'!I10-'Model inputs'!I41-'Model inputs'!I47) -> 19281.371 | J23: =IF('Model inputs'!J47="","",'Model inputs'!J33-'Model inputs'!J10-'Model inputs'!J41-'Model inputs'!J47) -> 19281.371 | K23: =IF('Model inputs'!K47="","",'Model inputs'!K33-'Model inputs'!K10-'Model inputs'!K41-'Model inputs'!K47) -> 19281.371 | L23: =IF('Model inputs'!L47="","",'Model inputs'!L33-'Model inputs'!L10-'Model inputs'!L41-'Model inputs'!L47) -> 19281.371 | ... S23: =IF('Model inputs'!S47="","",'Model inputs'!S33-'Model inputs'!S10-'Model inputs'!S41-'Model inputs'!S47) -> 19281.371
A24: Contribution > Harbor Bay | D24: =0 -> 0 | E24: =IF('Model inputs'!E48="","",'Model inputs'!E34-'Model inputs'!E11-'Model inputs'!E42-'Model inputs'!E48) -> 19281.371 | F24: =IF('Model inputs'!F48="","",'Model inputs'!F34-'Model inputs'!F11-'Model inputs'!F42-'Model inputs'!F48) -> 19281.371 | G24: =IF('Model inputs'!G48="","",'Model inputs'!G34-'Model inputs'!G11-'Model inputs'!G42-'Model inputs'!G48) -> 19281.371 | H24: =IF('Model inputs'!H48="","",'Model inputs'!H34-'Model inputs'!H11-'Model inputs'!H42-'Model inputs'!H48) -> 19281.371 | I24: =IF('Model inputs'!I48="","",'Model inputs'!I34-'Model inputs'!I11-'Model inputs'!I42-'Model inputs'!I48) -> 19281.371 | J24: =IF('Model inputs'!J48="","",'Model inputs'!J34-'Model inputs'!J11-'Model inputs'!J42-'Model inputs'!J48) -> 19281.371 | K24: =IF('Model inputs'!K48="","",'Model inputs'!K34-'Model inputs'!K11-'Model inputs'!K42-'Model inputs'!K48) -> 19281.371 | L24: =IF('Model inputs'!L48="","",'Model inputs'!L34-'Model inputs'!L11-'Model inputs'!L42-'Model inputs'!L48) -> 19281.371 | ... S24: =IF('Model inputs'!S48="","",'Model inputs'!S34-'Model inputs'!S11-'Model inputs'!S42-'Model inputs'!S48) -> 19281.371
A25: Contribution · Downside | D25: =SUM('Model inputs'!D154) -> 0 | E25: =IF('Model inputs'!E49="","",'Model inputs'!E35-'Model inputs'!E12-'Model inputs'!E43-'Model inputs'!E49) -> -4181.63
A26: Contribution · Growth | D26: =SUM('Model inputs'!D156) -> 0 | E26: =IF('Model inputs'!E50="","",'Model inputs'!E37-'Model inputs'!E13-'Model inputs'!E44-'Model inputs'!E50) -> 41732.406
A27: Conversion rate | C27: =SUM('Model inputs'!C28) -> 0.025
A28: Conversion rate > Harbor Bay | C28: ='Harbor Bay assumptions'!B6 -> 0.025
A29: Fulfillment cost | D29: =SUM('Model inputs'!D30) -> 0 | E29: =SUM('Model inputs'!E30) -> 15000 | F29: =SUM('Model inputs'!F30) -> 15000 | G29: =SUM('Model inputs'!G30) -> 15000 | H29: =SUM('Model inputs'!H30) -> 15000 | I29: =SUM('Model inputs'!I30) -> 15000 | J29: =SUM('Model inputs'!J30) -> 15000 | K29: =SUM('Model inputs'!K30) -> 15000 | ... S29: =SUM('Model inputs'!S30) -> 15000
A30: Fulfillment cost > Harbor Bay | D30: =0 -> 0 | E30: ='Model inputs'!E60*'Model inputs'!C32 -> 15000 | F30: ='Model inputs'!F60*'Model inputs'!C32 -> 15000 | G30: ='Model inputs'!G60*'Model inputs'!C32 -> 15000 | H30: ='Model inputs'!H60*'Model inputs'!C32 -> 15000 | I30: ='Model inputs'!I60*'Model inputs'!C32 -> 15000 | J30: ='Model inputs'!J60*'Model inputs'!C32 -> 15000 | K30: ='Model inputs'!K60*'Model inputs'!C32 -> 15000 | L30: ='Model inputs'!L60*'Model inputs'!C32 -> 15000 | M30: ='Model inputs'!M60*'Model inputs'!C32 -> 15000 | N30: ='Model inputs'!N60*'Model inputs'!C32 -> 15000 | O30: ='Model inputs'!O60*'Model inputs'!C32 -> 15000 | P30: ='Model inputs'!P60*'Model inputs'!C32 -> 15000 | Q30: ='Model inputs'!Q60*'Model inputs'!C32 -> 15000 | R30: ='Model inputs'!R60*'Model inputs'!C32 -> 15000 | S30: ='Model inputs'!S60*'Model inputs'!C32 -> 15000
A31: Fulfillment cost per order | C31: =SUM('Model inputs'!C32) -> 12
A32: Fulfillment cost per order > Harbor Bay | C32: ='Harbor Bay assumptions'!B9 -> 12
A33: Gross profit | D33: =SUM('Model inputs'!D34) -> 0 | E33: =SUM('Model inputs'!E34) -> 37781.371 | F33: =SUM('Model inputs'!F34) -> 37781.371 | G33: =SUM('Model inputs'!G34) -> 37781.371 | H33: =SUM('Model inputs'!H34) -> 37781.371 | I33: =SUM('Model inputs'!I34) -> 37781.371 | J33: =SUM('Model inputs'!J34) -> 37781.371 | K33: =SUM('Model inputs'!K34) -> 37781.371 | ... S33: =SUM('Model inputs'!S34) -> 37781.371
A34: Gross profit > Harbor Bay | D34: =0 -> 0 | E34: ='Model inputs'!E70-'Model inputs'!E66-'Model inputs'!E30 -> 37781.371 | F34: ='Model inputs'!F70-'Model inputs'!F66-'Model inputs'!F30 -> 37781.371 | G34: ='Model inputs'!G70-'Model inputs'!G66-'Model inputs'!G30 -> 37781.371 | H34: ='Model inputs'!H70-'Model inputs'!H66-'Model inputs'!H30 -> 37781.371 | I34: ='Model inputs'!I70-'Model inputs'!I66-'Model inputs'!I30 -> 37781.371 | J34: ='Model inputs'!J70-'Model inputs'!J66-'Model inputs'!J30 -> 37781.371 | K34: ='Model inputs'!K70-'Model inputs'!K66-'Model inputs'!K30 -> 37781.371 | L34: ='Model inputs'!L70-'Model inputs'!L66-'Model inputs'!L30 -> 37781.371 | ... S34: ='Model inputs'!S70-'Model inputs'!S66-'Model inputs'!S30 -> 37781.371
A35: Gross profit | D35: =SUM('Model inputs'!D36) -> 0 | E35: =SUM('Model inputs'!E36) -> 17818.37
A36: Gross profit > Harbor Bay | D36: ='Model inputs'!D34 -> 0 | E36: ='Model inputs'!E72-'Model inputs'!E146-'Model inputs'!E134 -> 17818.37
A37: Gross profit | D37: =SUM('Model inputs'!D38) -> 0 | E37: =SUM('Model inputs'!E38) -> 65732.406
A38: Gross profit > Harbor Bay | D38: ='Model inputs'!D34 -> 0 | E38: ='Model inputs'!E74-'Model inputs'!E148-'Model inputs'!E136 -> 65732.406
A39: Inference cost per month | C39: =SUM('Model inputs'!C40) -> 3000
A40: Inference cost per month > Harbor Bay | C40: ='Harbor Bay assumptions'!B11 -> 3000
A41: Inference expense | D41: =SUM('Model inputs'!D42) -> 0 | E41: =SUM('Model inputs'!E42) -> 3000 | F41: =SUM('Model inputs'!F42) -> 3000 | G41: =SUM('Model inputs'!G42) -> 3000 | H41: =SUM('Model inputs'!H42) -> 3000 | I41: =SUM('Model inputs'!I42) -> 3000 | J41: =SUM('Model inputs'!J42) -> 3000 | K41: =SUM('Model inputs'!K42) -> 3000 | ... S41: =SUM('Model inputs'!S42) -> 3000
A42: Inference expense > Harbor Bay | D42: =0 -> 0 | E42: =IF('Model inputs'!C40="","",'Model inputs'!C40) -> 3000 | F42: =IF('Model inputs'!C40="","",'Model inputs'!C40) -> 3000 | G42: =IF('Model inputs'!C40="","",'Model inputs'!C40) -> 3000 | H42: =IF('Model inputs'!C40="","",'Model inputs'!C40) -> 3000 | I42: =IF('Model inputs'!C40="","",'Model inputs'!C40) -> 3000 | J42: =IF('Model inputs'!C40="","",'Model inputs'!C40) -> 3000 | K42: =IF('Model inputs'!C40="","",'Model inputs'!C40) -> 3000 | L42: =IF('Model inputs'!C40="","",'Model inputs'!C40) -> 3000 | M42: =IF('Model inputs'!C40="","",'Model inputs'!C40) -> 3000 | N42: =IF('Model inputs'!C40="","",'Model inputs'!C40) -> 3000 | O42: =IF('Model inputs'!C40="","",'Model inputs'!C40) -> 3000 | P42: =IF('Model inputs'!C40="","",'Model inputs'!C40) -> 3000 | Q42: =IF('Model inputs'!C40="","",'Model inputs'!C40) -> 3000 | R42: =IF('Model inputs'!C40="","",'Model inputs'!C40) -> 3000 | S42: =IF('Model inputs'!C40="","",'Model inputs'!C40) -> 3000
A43: Inference expense · Downside | D43: =SUM('Model inputs'!D138) -> 0 | E43: =SUM('Model inputs'!E138) -> 3500
A44: Inference expense · Growth | D44: =SUM('Model inputs'!D140) -> 0 | E44: =SUM('Model inputs'!E140) -> 3500
A45: Infrastructure cost per month (synthetic demo) | C45: =SUM('Model inputs'!C46) -> 500
A46: Infrastructure cost per month (synthetic demo) > Harbor Bay | C46: ='Harbor Bay assumptions'!B12 -> 500
A47: Infrastructure expense | D47: =SUM('Model inputs'!D48) -> 0 | E47: =IF('Model inputs'!C46="","",'Model inputs'!C46) -> 500 | F47: =IF('Model inputs'!C46="","",'Model inputs'!C46) -> 500 | G47: =IF('Model inputs'!C46="","",'Model inputs'!C46) -> 500 | H47: =IF('Model inputs'!C46="","",'Model inputs'!C46) -> 500 | I47: =IF('Model inputs'!C46="","",'Model inputs'!C46) -> 500 | J47: =IF('Model inputs'!C46="","",'Model inputs'!C46) -> 500 | K47: =IF('Model inputs'!C46="","",'Model inputs'!C46) -> 500 | L47: =IF('Model inputs'!C46="","",'Model inputs'!C46) -> 500 | M47: =IF('Model inputs'!C46="","",'Model inputs'!C46) -> 500 | N47: =IF('Model inputs'!C46="","",'Model inputs'!C46) -> 500 | O47: =IF('Model inputs'!C46="","",'Model inputs'!C46) -> 500 | P47: =IF('Model inputs'!C46="","",'Model inputs'!C46) -> 500 | Q47: =IF('Model inputs'!C46="","",'Model inputs'!C46) -> 500 | R47: =IF('Model inputs'!C46="","",'Model inputs'!C46) -> 500 | S47: =IF('Model inputs'!C46="","",'Model inputs'!C46) -> 500
A48: Infrastructure expense > Harbor Bay | D48: =0 -> 0 | E48: =IF('Model inputs'!C46="","",'Model inputs'!C46) -> 500 | F48: =IF('Model inputs'!C46="","",'Model inputs'!C46) -> 500 | G48: =IF('Model inputs'!C46="","",'Model inputs'!C46) -> 500 | H48: =IF('Model inputs'!C46="","",'Model inputs'!C46) -> 500 | I48: =IF('Model inputs'!C46="","",'Model inputs'!C46) -> 500 | J48: =IF('Model inputs'!C46="","",'Model inputs'!C46) -> 500 | K48: =IF('Model inputs'!C46="","",'Model inputs'!C46) -> 500 | L48: =IF('Model inputs'!C46="","",'Model inputs'!C46) -> 500 | M48: =IF('Model inputs'!C46="","",'Model inputs'!C46) -> 500 | N48: =IF('Model inputs'!C46="","",'Model inputs'!C46) -> 500 | O48: =IF('Model inputs'!C46="","",'Model inputs'!C46) -> 500 | P48: =IF('Model inputs'!C46="","",'Model inputs'!C46) -> 500 | Q48: =IF('Model inputs'!C46="","",'Model inputs'!C46) -> 500 | R48: =IF('Model inputs'!C46="","",'Model inputs'!C46) -> 500 | S48: =IF('Model inputs'!C46="","",'Model inputs'!C46) -> 500
A49: Infrastructure expense · Downside | D49: =SUM('Model inputs'!D158) -> 0 | E49: =IF('Model inputs'!C142="","",'Model inputs'!C142) -> 500
A50: Infrastructure expense · Growth | D50: =SUM('Model inputs'!D160) -> 0 | E50: =IF('Model inputs'!C144="","",'Model inputs'!C144) -> 500
A51: Monthly visits | C51: =SUM('Model inputs'!C52) -> 50000
A52: Monthly visits > Harbor Bay | C52: ='Harbor Bay assumptions'!B5 -> 50000
A53: Opening cash (synthetic demo) | C53: =SUM('Model inputs'!C54) -> 30000
A54: Opening cash (synthetic demo) > Harbor Bay | C54: ='Harbor Bay assumptions'!B13 -> 30000
A55: Opening cash (synthetic demo) | C55: =SUM('Model inputs'!C56) -> 30000
A56: Opening cash (synthetic demo) > Harbor Bay | C56: ='Scenario assumptions side by si'!D13 -> 30000
A57: Opening cash (synthetic demo) | C57: =SUM('Model inputs'!C58) -> 30000
A58: Opening cash (synthetic demo) > Harbor Bay | C58: ='Harbor Bay assumptions'!B13 -> 30000
A59: Orders | D59: =SUM('Model inputs'!D60) -> 0 | E59: =SUM('Model inputs'!E60) -> 1250 | F59: =SUM('Model inputs'!F60) -> 1250 | G59: =SUM('Model inputs'!G60) -> 1250 | H59: =SUM('Model inputs'!H60) -> 1250 | I59: =SUM('Model inputs'!I60) -> 1250 | J59: =SUM('Model inputs'!J60) -> 1250 | K59: =SUM('Model inputs'!K60) -> 1250 | ... S59: =SUM('Model inputs'!S60) -> 1250
A60: Orders > Harbor Bay | D60: =0 -> 0 | E60: ='Model inputs'!E76*'Model inputs'!C28 -> 1250 | F60: ='Model inputs'!F76*'Model inputs'!C28 -> 1250 | G60: ='Model inputs'!G76*'Model inputs'!C28 -> 1250 | H60: ='Model inputs'!H76*'Model inputs'!C28 -> 1250 | I60: ='Model inputs'!I76*'Model inputs'!C28 -> 1250 | J60: ='Model inputs'!J76*'Model inputs'!C28 -> 1250 | K60: ='Model inputs'!K76*'Model inputs'!C28 -> 1250 | L60: ='Model inputs'!L76*'Model inputs'!C28 -> 1250 | M60: ='Model inputs'!M76*'Model inputs'!C28 -> 1250 | N60: ='Model inputs'!N76*'Model inputs'!C28 -> 1250 | O60: ='Model inputs'!O76*'Model inputs'!C28 -> 1250 | P60: ='Model inputs'!P76*'Model inputs'!C28 -> 1250 | Q60: ='Model inputs'!Q76*'Model inputs'!C28 -> 1250 | R60: ='Model inputs'!R76*'Model inputs'!C28 -> 1250 | S60: ='Model inputs'!S76*'Model inputs'!C28 -> 1250
A61: Orders | D61: =SUM('Model inputs'!D62) -> 0 | E61: =SUM('Model inputs'!E62) -> 720
A62: Orders > Harbor Bay | D62: ='Model inputs'!D60 -> 0 | E62: ='Model inputs'!E150*'Scenario assumptions side by si'!D6 -> 720
A63: Orders | D63: =SUM('Model inputs'!D64) -> 0 | E63: =SUM('Model inputs'!E64) -> 1950
A64: Orders > Harbor Bay | D64: ='Model inputs'!D60 -> 0 | E64: ='Model inputs'!E152*'Scenario assumptions side by si'!C6 -> 1950
A65: Product cost | D65: =SUM('Model inputs'!D66) -> 0 | E65: =SUM('Model inputs'!E66) -> 53468.629 | F65: =SUM('Model inputs'!F66) -> 53468.629 | G65: =SUM('Model inputs'!G66) -> 53468.629 | H65: =SUM('Model inputs'!H66) -> 53468.629 | I65: =SUM('Model inputs'!I66) -> 53468.629 | J65: =SUM('Model inputs'!J66) -> 53468.629 | K65: =SUM('Model inputs'!K66) -> 53468.629 | ... S65: =SUM('Model inputs'!S66) -> 53468.629
A66: Product cost > Harbor Bay | D66: =0 -> 0 | E66: ='Model inputs'!E60*'Model inputs'!C68 -> 53468.629 | F66: ='Model inputs'!F60*'Model inputs'!C68 -> 53468.629 | G66: ='Model inputs'!G60*'Model inputs'!C68 -> 53468.629 | H66: ='Model inputs'!H60*'Model inputs'!C68 -> 53468.629 | I66: ='Model inputs'!I60*'Model inputs'!C68 -> 53468.629 | J66: ='Model inputs'!J60*'Model inputs'!C68 -> 53468.629 | K66: ='Model inputs'!K60*'Model inputs'!C68 -> 53468.629 | L66: ='Model inputs'!L60*'Model inputs'!C68 -> 53468.629 | M66: ='Model inputs'!M60*'Model inputs'!C68 -> 53468.629 | N66: ='Model inputs'!N60*'Model inputs'!C68 -> 53468.629 | O66: ='Model inputs'!O60*'Model inputs'!C68 -> 53468.629 | P66: ='Model inputs'!P60*'Model inputs'!C68 -> 53468.629 | Q66: ='Model inputs'!Q60*'Model inputs'!C68 -> 53468.629 | R66: ='Model inputs'!R60*'Model inputs'!C68 -> 53468.629 | S66: ='Model inputs'!S60*'Model inputs'!C68 -> 53468.629
A67: Product cost per order (provisional) | C67: =SUM('Model inputs'!C68) -> 42.774903
A68: Product cost per order (provisional) > Harbor Bay | C68: ='Model inputs'!B7*'Model inputs'!B20 -> 42.774903
A69: Revenue | D69: =SUM('Model inputs'!D70) -> 0 | E69: =SUM('Model inputs'!E70) -> 106250 | F69: =SUM('Model inputs'!F70) -> 106250 | G69: =SUM('Model inputs'!G70) -> 106250 | H69: =SUM('Model inputs'!H70) -> 106250 | I69: =SUM('Model inputs'!I70) -> 106250 | J69: =SUM('Model inputs'!J70) -> 106250 | K69: =SUM('Model inputs'!K70) -> 106250 | ... S69: =SUM('Model inputs'!S70) -> 106250
A70: Revenue > Harbor Bay | D70: =0 -> 0 | E70: ='Model inputs'!E60*'Model inputs'!B7 -> 106250 | F70: ='Model inputs'!F60*'Model inputs'!B7 -> 106250 | G70: ='Model inputs'!G60*'Model inputs'!B7 -> 106250 | H70: ='Model inputs'!H60*'Model inputs'!B7 -> 106250 | I70: ='Model inputs'!I60*'Model inputs'!B7 -> 106250 | J70: ='Model inputs'!J60*'Model inputs'!B7 -> 106250 | K70: ='Model inputs'!K60*'Model inputs'!B7 -> 106250 | L70: ='Model inputs'!L60*'Model inputs'!B7 -> 106250 | M70: ='Model inputs'!M60*'Model inputs'!B7 -> 106250 | N70: ='Model inputs'!N60*'Model inputs'!B7 -> 106250 | O70: ='Model inputs'!O60*'Model inputs'!B7 -> 106250 | P70: ='Model inputs'!P60*'Model inputs'!B7 -> 106250 | Q70: ='Model inputs'!Q60*'Model inputs'!B7 -> 106250 | R70: ='Model inputs'!R60*'Model inputs'!B7 -> 106250 | S70: ='Model inputs'!S60*'Model inputs'!B7 -> 106250
A71: Revenue | D71: =SUM('Model inputs'!D72) -> 0 | E71: =SUM('Model inputs'!E72) -> 56160
A72: Revenue > Harbor Bay | D72: ='Model inputs'!D70 -> 0 | E72: ='Model inputs'!E62*'Scenario assumptions side by si'!D7 -> 56160
A73: Revenue | D73: =SUM('Model inputs'!D74) -> 0 | E73: =SUM('Model inputs'!E74) -> 175500
A74: Revenue > Harbor Bay | D74: ='Model inputs'!D70 -> 0 | E74: ='Model inputs'!E64*'Scenario assumptions side by si'!C7 -> 175500
A75: Visits | D75: =SUM('Model inputs'!D76) -> 0 | E75: =SUM('Model inputs'!E76) -> 50000 | F75: =SUM('Model inputs'!F76) -> 50000 | G75: =SUM('Model inputs'!G76) -> 50000 | H75: =SUM('Model inputs'!H76) -> 50000 | I75: =SUM('Model inputs'!I76) -> 50000 | J75: =SUM('Model inputs'!J76) -> 50000 | K75: =SUM('Model inputs'!K76) -> 50000 | ... S75: =SUM('Model inputs'!S76) -> 50000
A76: Visits > Harbor Bay | D76: =0 -> 0 | E76: =IF('Model inputs'!C52="","",'Model inputs'!C52) -> 50000 | F76: =IF('Model inputs'!C52="","",'Model inputs'!C52) -> 50000 | G76: =IF('Model inputs'!C52="","",'Model inputs'!C52) -> 50000 | H76: =IF('Model inputs'!C52="","",'Model inputs'!C52) -> 50000 | I76: =IF('Model inputs'!C52="","",'Model inputs'!C52) -> 50000 | J76: =IF('Model inputs'!C52="","",'Model inputs'!C52) -> 50000 | K76: =IF('Model inputs'!C52="","",'Model inputs'!C52) -> 50000 | L76: =IF('Model inputs'!C52="","",'Model inputs'!C52) -> 50000 | M76: =IF('Model inputs'!C52="","",'Model inputs'!C52) -> 50000 | N76: =IF('Model inputs'!C52="","",'Model inputs'!C52) -> 50000 | O76: =IF('Model inputs'!C52="","",'Model inputs'!C52) -> 50000 | P76: =IF('Model inputs'!C52="","",'Model inputs'!C52) -> 50000 | Q76: =IF('Model inputs'!C52="","",'Model inputs'!C52) -> 50000 | R76: =IF('Model inputs'!C52="","",'Model inputs'!C52) -> 50000 | S76: =IF('Model inputs'!C52="","",'Model inputs'!C52) -> 50000
A77: Assumed basket cost total · Harbor Bay assumptions | B77: =SUM('Model inputs'!B80,'Model inputs'!B81,'Model inputs'!B82,'Model inputs'!B83,'Model inputs'!B84,'Model inputs'!B85,'Model inputs'!B86,'Model inputs'!B87) -> 389
A78: Assumed basket price total · Harbor Bay assumptions | B78: =SUM('Model inputs'!B89,'Model inputs'!B90,'Model inputs'!B91,'Model inputs'!B92,'Model inputs'!B93,'Model inputs'!B94,'Model inputs'!B95,'Model inputs'!B96) -> 773
A79: Weighted catalog cost | B79: ='Model inputs'!B106*'Model inputs'!B97 -> 0
A80: Weighted catalog cost > boots | B80: ='Model inputs'!B107*'Model inputs'!B98 -> 65
A81: Weighted catalog cost > bottle | B81: ='Model inputs'!B108*'Model inputs'!B99 -> 15
A82: Weighted catalog cost > charger | B82: ='Model inputs'!B109*'Model inputs'!B100 -> 22
A83: Weighted catalog cost > lights | B83: ='Model inputs'!B110*'Model inputs'!B101 -> 7
A84: Weighted catalog cost > pack | B84: ='Model inputs'!B111*'Model inputs'!B102 -> 85
A85: Weighted catalog cost > poles | B85: ='Model inputs'!B112*'Model inputs'!B103 -> 45
A86: Weighted catalog cost > pouch | B86: ='Model inputs'!B113*'Model inputs'!B104 -> 10
A87: Weighted catalog cost > tent | B87: ='Model inputs'!B114*'Model inputs'!B105 -> 140
A88: Weighted catalog price | B88: ='Model inputs'!B115*'Model inputs'!B97 -> 0
A89: Weighted catalog price > boots | B89: ='Model inputs'!B116*'Model inputs'!B98 -> 120
A90: Weighted catalog price > bottle | B90: ='Model inputs'!B117*'Model inputs'!B99 -> 35
A91: Weighted catalog price > charger | B91: ='Model inputs'!B118*'Model inputs'!B100 -> 45
A92: Weighted catalog price > lights | B92: ='Model inputs'!B119*'Model inputs'!B101 -> 18
A93: Weighted catalog price > pack | B93: ='Model inputs'!B120*'Model inputs'!B102 -> 160
A94: Weighted catalog price > poles | B94: ='Model inputs'!B121*'Model inputs'!B103 -> 90
A95: Weighted catalog price > pouch | B95: ='Model inputs'!B122*'Model inputs'!B104 -> 25
A96: Weighted catalog price > tent | B96: ='Model inputs'!B123*'Model inputs'!B105 -> 280
A97: Assumed unit mix weight (provisional) | B97: 0
A98: Assumed unit mix weight (provisional) > boots | B98: ='Seed product catalog — provisio'!F5 -> 1
A99: Assumed unit mix weight (provisional) > bottle | B99: ='Seed product catalog — provisio'!F6 -> 1
A100: Assumed unit mix weight (provisional) > charger | B100: ='Seed product catalog — provisio'!F7 -> 1
A101: Assumed unit mix weight (provisional) > lights | B101: ='Seed product catalog — provisio'!F8 -> 1
...
